{
  "id": "GD챌린저_임명훈_1",
  "name": "임명훈",
  "team": "GD챌린저스BC(U-18)",
  "position": "투수",
  "season": 2026,
  "gameLog": [
    {
      "gameId": "37034",
      "date": "2026-03-21",
      "opponent": "경기고",
      "line": "1.2이닝 0자책 1탈삼진"
    }
  ],
  "number": "1",
  "bats": "우",
  "throws": "우",
  "grade": "3",
  "personNo": "201803001644",
  "region": "서울",
  "pitching": {
    "g": 1,
    "w": 0,
    "l": 0,
    "sv": 0,
    "ip": 1.2,
    "h": 2,
    "r": 2,
    "er": 0,
    "bb": 1,
    "so": 1,
    "era": 0,
    "whip": 1.8
  }
}
