{"id":"김포과학기술고_김지왕_27","name":"김지왕","team":"김포과학기술고","position":"투수","season":2026,"gameLog":[{"gameId":"37853","date":"2026-05-23","opponent":"유신고","line":"0이닝 0자책 0탈삼진","title":"2026 고교야구 주말리그 후반기(경기·인천권)","pStat":{"outs":0,"h":0,"r":0,"er":0,"bb":2,"so":0,"w":0,"l":0,"sv":0}},{"gameId":"37732","date":"2026-05-05","opponent":"광주제일","line":"0이닝 0자책 0탈삼진","title":"제80회 황금사자기 전국고교야구대회 겸 주말리그 왕중왕전","pStat":{"outs":0,"h":0,"r":0,"er":0,"bb":2,"so":0,"w":0,"l":0,"sv":0}},{"gameId":"37672","date":"2026-04-26","opponent":"경민IT","line":"4이닝 0자책 2탈삼진","title":"2026 고교야구 주말리그 전반기(경기권B)","pStat":{"outs":12,"h":0,"r":0,"er":0,"bb":2,"so":2,"w":0,"l":0,"sv":0}}],"number":"27","bats":"우","throws":"우","grade":"3","personNo":"201808002113","region":"경기","pitching":{"g":3,"w":0,"l":0,"sv":0,"ip":4,"h":0,"hr":0,"r":0,"er":0,"bb":6,"so":2,"bf":16,"np":55,"era":0,"whip":1.5}}