{
  "id": "제물포고_정기문_5",
  "name": "정기문",
  "team": "제물포고",
  "position": "내야수",
  "season": 2026,
  "gameLog": [
    {
      "gameId": "37469",
      "date": "2026-04-19",
      "opponent": "비봉고",
      "line": "3타수 0안타 1볼넷"
    },
    {
      "gameId": "37466",
      "date": "2026-04-18",
      "opponent": "안산공업고",
      "line": "5타수 2안타"
    },
    {
      "gameId": "37511",
      "date": "2026-04-08",
      "opponent": "광주제일",
      "line": "4타수 0안타 1볼넷"
    },
    {
      "gameId": "37504",
      "date": "2026-04-06",
      "opponent": "개성고",
      "line": "3타수 0안타 1볼넷"
    },
    {
      "gameId": "37490",
      "date": "2026-04-03",
      "opponent": "장충고",
      "line": "5타수 1안타 1볼넷"
    },
    {
      "gameId": "37367",
      "date": "2026-03-31",
      "opponent": "거제BC(",
      "line": "4타수 0안타 1볼넷"
    },
    {
      "gameId": "37327",
      "date": "2026-03-28",
      "opponent": "선린인터넷",
      "line": "3타수 1안타 2볼넷"
    }
  ],
  "number": "5",
  "bats": "좌",
  "throws": "우",
  "grade": "3",
  "personNo": "202202001877",
  "region": "인천",
  "batting": {
    "g": 7,
    "pa": 35,
    "ab": 27,
    "r": 7,
    "h": 4,
    "b2": 0,
    "b3": 1,
    "hr": 0,
    "rbi": 0,
    "bb": 7,
    "hbp": 1,
    "so": 9,
    "sb": 5,
    "avg": 0.148,
    "obp": 0.343,
    "slg": 0.222
  }
}
