{"season":2025,"lastUpdated":"2026-07-13T01:27:32.637Z","gameCount":57,"source":"korea-baseball.com (KBSA)","teamGames":{"강릉고":1,"거제BC(U-18)":1,"경기고":2,"경기상업고":1,"경기항공고":5,"덕수고":6,"경남고":4,"비봉고":2,"선린인터넷고":1,"경북고":2,"의성고":1,"울산공고BC":1,"광주제일고":1,"광주진흥고":1,"야로고BC":2,"김해고":1,"대구상원고":5,"대전고":2,"도개고":1,"동산고":2,"라온고":2,"마산용마고":4,"밀양BC(U-18)":1,"백송고":3,"부산고":6,"부산공업고":2,"북일고":2,"상동고":3,"서울고":3,"서울동산고":1,"서울컨벤션고":1,"설악고":1,"성남고":2,"세광고":2,"EPBC(U-18)":1,"세원고":3,"순천효천고BC":1,"신일고":1,"신흥고":1,"아산BC(U-18)":1,"안산공업고":1,"전북인공지능고":2,"예일메디텍고":2,"화성동탄B(U-18)":1,"유신고":2,"의왕BC(U-18)":1,"인천고":4,"장안고":1,"장충고":2,"전주고":3,"제주고":1,"진영고":2,"청원고":1,"충훈고":2,"화순고":1,"휘문고":3,"GD챌린저스BC(U-18)":1,"TNPBA(U-18)":1}}