{
  "id": "32346",
  "date": "2024-07-10",
  "season": 2024,
  "home": "청주고",
  "away": "전주고",
  "score": {
    "home": 0,
    "away": 13
  },
  "title": "제79회 청룡기 전국고교야구선수권대회 겸 주말리그 왕중왕전",
  "batters": [
    {
      "playerId": "전주고_박한결_6",
      "name": "박한결",
      "team": "전주고",
      "ab": 4,
      "h": 1,
      "rbi": 1,
      "r": 1,
      "b2": 0,
      "b3": 0,
      "hr": 0,
      "bb": 0,
      "hbp": 1,
      "so": 0,
      "sb": 1
    },
    {
      "playerId": "전주고_최윤석_14",
      "name": "최윤석",
      "team": "전주고",
      "ab": 1,
      "h": 0,
      "rbi": 0,
      "r": 2,
      "b2": 0,
      "b3": 0,
      "hr": 0,
      "bb": 2,
      "hbp": 1,
      "so": 0,
      "sb": 0
    },
    {
      "playerId": "전주고_엄준현_7",
      "name": "엄준현",
      "team": "전주고",
      "ab": 2,
      "h": 1,
      "rbi": 1,
      "r": 2,
      "b2": 0,
      "b3": 0,
      "hr": 0,
      "bb": 0,
      "hbp": 2,
      "so": 0,
      "sb": 1
    },
    {
      "playerId": "전주고_이한림_22",
      "name": "이한림",
      "team": "전주고",
      "ab": 3,
      "h": 2,
      "rbi": 4,
      "r": 1,
      "b2": 0,
      "b3": 0,
      "hr": 0,
      "bb": 0,
      "hbp": 1,
      "so": 0,
      "sb": 0
    },
    {
      "playerId": "전주고_서영준_53",
      "name": "서영준",
      "team": "전주고",
      "ab": 3,
      "h": 1,
      "rbi": 1,
      "r": 1,
      "b2": 0,
      "b3": 0,
      "hr": 0,
      "bb": 0,
      "hbp": 0,
      "so": 1,
      "sb": 0
    },
    {
      "playerId": "전주고_최성음_54",
      "name": "최성음",
      "team": "전주고",
      "ab": 0,
      "h": 0,
      "rbi": 0,
      "r": 1,
      "b2": 0,
      "b3": 0,
      "hr": 0,
      "bb": 1,
      "hbp": 0,
      "so": 0,
      "sb": 0
    },
    {
      "playerId": "전주고_성민수_9",
      "name": "성민수",
      "team": "전주고",
      "ab": 3,
      "h": 1,
      "rbi": 1,
      "r": 1,
      "b2": 0,
      "b3": 0,
      "hr": 0,
      "bb": 0,
      "hbp": 0,
      "so": 1,
      "sb": 0
    },
    {
      "playerId": "전주고_정석주_8",
      "name": "정석주",
      "team": "전주고",
      "ab": 0,
      "h": 0,
      "rbi": 0,
      "r": 0,
      "b2": 0,
      "b3": 0,
      "hr": 0,
      "bb": 1,
      "hbp": 0,
      "so": 0,
      "sb": 0
    },
    {
      "playerId": "전주고_김유빈_25",
      "name": "김유빈",
      "team": "전주고",
      "ab": 2,
      "h": 1,
      "rbi": 2,
      "r": 2,
      "b2": 1,
      "b3": 0,
      "hr": 0,
      "bb": 0,
      "hbp": 1,
      "so": 0,
      "sb": 0
    },
    {
      "playerId": "전주고_송관우_15",
      "name": "송관우",
      "team": "전주고",
      "ab": 1,
      "h": 0,
      "rbi": 0,
      "r": 0,
      "b2": 0,
      "b3": 0,
      "hr": 0,
      "bb": 0,
      "hbp": 0,
      "so": 1,
      "sb": 0
    },
    {
      "playerId": "전주고_윤도연_51",
      "name": "윤도연",
      "team": "전주고",
      "ab": 3,
      "h": 2,
      "rbi": 1,
      "r": 2,
      "b2": 0,
      "b3": 0,
      "hr": 0,
      "bb": 0,
      "hbp": 1,
      "so": 1,
      "sb": 0
    },
    {
      "playerId": "전주고_김서준_3",
      "name": "김서준",
      "team": "전주고",
      "ab": 2,
      "h": 0,
      "rbi": 0,
      "r": 0,
      "b2": 0,
      "b3": 0,
      "hr": 0,
      "bb": 0,
      "hbp": 0,
      "so": 1,
      "sb": 0
    },
    {
      "playerId": "전주고_유재민_43",
      "name": "유재민",
      "team": "전주고",
      "ab": 1,
      "h": 1,
      "rbi": 0,
      "r": 0,
      "b2": 0,
      "b3": 0,
      "hr": 0,
      "bb": 0,
      "hbp": 0,
      "so": 0,
      "sb": 0
    },
    {
      "playerId": "전주고_이호민_1",
      "name": "이호민",
      "team": "전주고",
      "ab": 1,
      "h": 1,
      "rbi": 0,
      "r": 0,
      "b2": 0,
      "b3": 0,
      "hr": 0,
      "bb": 0,
      "hbp": 0,
      "so": 0,
      "sb": 0
    },
    {
      "playerId": "청주고_현빈_1",
      "name": "현빈",
      "team": "청주고",
      "ab": 2,
      "h": 0,
      "rbi": 0,
      "r": 0,
      "b2": 0,
      "b3": 0,
      "hr": 0,
      "bb": 0,
      "hbp": 0,
      "so": 0,
      "sb": 0
    },
    {
      "playerId": "청주고_조백경_58",
      "name": "조백경",
      "team": "청주고",
      "ab": 2,
      "h": 0,
      "rbi": 0,
      "r": 0,
      "b2": 0,
      "b3": 0,
      "hr": 0,
      "bb": 0,
      "hbp": 0,
      "so": 1,
      "sb": 0
    },
    {
      "playerId": "청주고_정제은_52",
      "name": "정제은",
      "team": "청주고",
      "ab": 2,
      "h": 1,
      "rbi": 0,
      "r": 0,
      "b2": 0,
      "b3": 0,
      "hr": 0,
      "bb": 0,
      "hbp": 0,
      "so": 0,
      "sb": 0
    },
    {
      "playerId": "청주고_남관무_51",
      "name": "남관무",
      "team": "청주고",
      "ab": 2,
      "h": 0,
      "rbi": 0,
      "r": 0,
      "b2": 0,
      "b3": 0,
      "hr": 0,
      "bb": 0,
      "hbp": 0,
      "so": 0,
      "sb": 0
    },
    {
      "playerId": "청주고_서승운_6",
      "name": "서승운",
      "team": "청주고",
      "ab": 2,
      "h": 0,
      "rbi": 0,
      "r": 0,
      "b2": 0,
      "b3": 0,
      "hr": 0,
      "bb": 0,
      "hbp": 0,
      "so": 0,
      "sb": 0
    },
    {
      "playerId": "청주고_이주원_42",
      "name": "이주원",
      "team": "청주고",
      "ab": 2,
      "h": 1,
      "rbi": 0,
      "r": 0,
      "b2": 1,
      "b3": 0,
      "hr": 0,
      "bb": 0,
      "hbp": 0,
      "so": 1,
      "sb": 0
    },
    {
      "playerId": "청주고_강동현_24",
      "name": "강동현",
      "team": "청주고",
      "ab": 1,
      "h": 0,
      "rbi": 0,
      "r": 0,
      "b2": 0,
      "b3": 0,
      "hr": 0,
      "bb": 0,
      "hbp": 0,
      "so": 0,
      "sb": 0
    },
    {
      "playerId": "청주고_조이서_50",
      "name": "조이서",
      "team": "청주고",
      "ab": 1,
      "h": 0,
      "rbi": 0,
      "r": 0,
      "b2": 0,
      "b3": 0,
      "hr": 0,
      "bb": 0,
      "hbp": 0,
      "so": 0,
      "sb": 0
    },
    {
      "playerId": "청주고_김학래_5",
      "name": "김학래",
      "team": "청주고",
      "ab": 2,
      "h": 0,
      "rbi": 0,
      "r": 0,
      "b2": 0,
      "b3": 0,
      "hr": 0,
      "bb": 0,
      "hbp": 0,
      "so": 0,
      "sb": 0
    },
    {
      "playerId": "청주고_박종인_32",
      "name": "박종인",
      "team": "청주고",
      "ab": 1,
      "h": 0,
      "rbi": 0,
      "r": 0,
      "b2": 0,
      "b3": 0,
      "hr": 0,
      "bb": 0,
      "hbp": 0,
      "so": 1,
      "sb": 0
    }
  ],
  "pitchers": [
    {
      "playerId": "전주고_이호민_1",
      "name": "이호민",
      "team": "전주고",
      "outs": 10,
      "h": 1,
      "r": 0,
      "er": 0,
      "bb": 0,
      "so": 3,
      "w": 0,
      "l": 0,
      "sv": 0
    },
    {
      "playerId": "전주고_송관우_15",
      "name": "송관우",
      "team": "전주고",
      "outs": 5,
      "h": 1,
      "r": 0,
      "er": 0,
      "bb": 0,
      "so": 0,
      "w": 1,
      "l": 0,
      "sv": 0
    },
    {
      "playerId": "청주고_엄태현_31",
      "name": "엄태현",
      "team": "청주고",
      "outs": 2,
      "h": 2,
      "r": 4,
      "er": 4,
      "bb": 2,
      "so": 0,
      "w": 0,
      "l": 1,
      "sv": 0
    },
    {
      "playerId": "청주고_손시우_46",
      "name": "손시우",
      "team": "청주고",
      "outs": 6,
      "h": 3,
      "r": 6,
      "er": 3,
      "bb": 4,
      "so": 2,
      "w": 0,
      "l": 0,
      "sv": 0
    },
    {
      "playerId": "청주고_이정민_59",
      "name": "이정민",
      "team": "청주고",
      "outs": 0,
      "h": 1,
      "r": 1,
      "er": 1,
      "bb": 2,
      "so": 0,
      "w": 0,
      "l": 0,
      "sv": 0
    },
    {
      "playerId": "청주고_강민준_55",
      "name": "강민준",
      "team": "청주고",
      "outs": 2,
      "h": 0,
      "r": 0,
      "er": 0,
      "bb": 0,
      "so": 2,
      "w": 0,
      "l": 0,
      "sv": 0
    },
    {
      "playerId": "청주고_한현우_47",
      "name": "한현우",
      "team": "청주고",
      "outs": 3,
      "h": 3,
      "r": 1,
      "er": 1,
      "bb": 1,
      "so": 0,
      "w": 0,
      "l": 0,
      "sv": 0
    },
    {
      "playerId": "청주고_홍우현_41",
      "name": "홍우현",
      "team": "청주고",
      "outs": 1,
      "h": 0,
      "r": 1,
      "er": 1,
      "bb": 2,
      "so": 1,
      "w": 0,
      "l": 0,
      "sv": 0
    },
    {
      "playerId": "청주고_이승근_21",
      "name": "이승근",
      "team": "청주고",
      "outs": 1,
      "h": 2,
      "r": 0,
      "er": 0,
      "bb": 0,
      "so": 0,
      "w": 0,
      "l": 0,
      "sv": 0
    }
  ],
  "matchups": [
    {
      "batterId": "전주고_박한결_6",
      "pitcherId": "청주고_엄태현_31",
      "ab": 1,
      "h": 0,
      "b2": 0,
      "b3": 0,
      "hr": 0,
      "bb": 0,
      "hbp": 0,
      "so": 0
    },
    {
      "batterId": "전주고_박한결_6",
      "pitcherId": "청주고_손시우_46",
      "ab": 1,
      "h": 0,
      "b2": 0,
      "b3": 0,
      "hr": 0,
      "bb": 0,
      "hbp": 1,
      "so": 0
    },
    {
      "batterId": "전주고_박한결_6",
      "pitcherId": "청주고_강민준_55",
      "ab": 1,
      "h": 1,
      "b2": 0,
      "b3": 0,
      "hr": 0,
      "bb": 0,
      "hbp": 0,
      "so": 0
    },
    {
      "batterId": "전주고_박한결_6",
      "pitcherId": "청주고_한현우_47",
      "ab": 1,
      "h": 0,
      "b2": 0,
      "b3": 0,
      "hr": 0,
      "bb": 0,
      "hbp": 0,
      "so": 0
    },
    {
      "batterId": "전주고_최윤석_14",
      "pitcherId": "청주고_엄태현_31",
      "ab": 1,
      "h": 0,
      "b2": 0,
      "b3": 0,
      "hr": 0,
      "bb": 0,
      "hbp": 0,
      "so": 0
    },
    {
      "batterId": "전주고_최윤석_14",
      "pitcherId": "청주고_손시우_46",
      "ab": 0,
      "h": 0,
      "b2": 0,
      "b3": 0,
      "hr": 0,
      "bb": 1,
      "hbp": 1,
      "so": 0
    },
    {
      "batterId": "전주고_최윤석_14",
      "pitcherId": "청주고_강민준_55",
      "ab": 0,
      "h": 0,
      "b2": 0,
      "b3": 0,
      "hr": 0,
      "bb": 1,
      "hbp": 0,
      "so": 0
    },
    {
      "batterId": "전주고_엄준현_7",
      "pitcherId": "청주고_엄태현_31",
      "ab": 0,
      "h": 0,
      "b2": 0,
      "b3": 0,
      "hr": 0,
      "bb": 0,
      "hbp": 1,
      "so": 0
    },
    {
      "batterId": "전주고_엄준현_7",
      "pitcherId": "청주고_손시우_46",
      "ab": 1,
      "h": 1,
      "b2": 0,
      "b3": 0,
      "hr": 0,
      "bb": 0,
      "hbp": 1,
      "so": 0
    },
    {
      "batterId": "전주고_엄준현_7",
      "pitcherId": "청주고_강민준_55",
      "ab": 1,
      "h": 0,
      "b2": 0,
      "b3": 0,
      "hr": 0,
      "bb": 0,
      "hbp": 0,
      "so": 0
    },
    {
      "batterId": "전주고_이한림_22",
      "pitcherId": "청주고_엄태현_31",
      "ab": 0,
      "h": 0,
      "b2": 0,
      "b3": 0,
      "hr": 0,
      "bb": 0,
      "hbp": 1,
      "so": 0
    },
    {
      "batterId": "전주고_이한림_22",
      "pitcherId": "청주고_손시우_46",
      "ab": 2,
      "h": 2,
      "b2": 0,
      "b3": 0,
      "hr": 0,
      "bb": 0,
      "hbp": 0,
      "so": 0
    },
    {
      "batterId": "전주고_이한림_22",
      "pitcherId": "청주고_한현우_47",
      "ab": 1,
      "h": 0,
      "b2": 0,
      "b3": 0,
      "hr": 0,
      "bb": 0,
      "hbp": 0,
      "so": 0
    },
    {
      "batterId": "전주고_서영준_53",
      "pitcherId": "청주고_엄태현_31",
      "ab": 1,
      "h": 1,
      "b2": 0,
      "b3": 0,
      "hr": 0,
      "bb": 0,
      "hbp": 0,
      "so": 0
    },
    {
      "batterId": "전주고_서영준_53",
      "pitcherId": "청주고_손시우_46",
      "ab": 2,
      "h": 0,
      "b2": 0,
      "b3": 0,
      "hr": 0,
      "bb": 0,
      "hbp": 0,
      "so": 1
    },
    {
      "batterId": "전주고_최성음_54",
      "pitcherId": "청주고_한현우_47",
      "ab": 0,
      "h": 0,
      "b2": 0,
      "b3": 0,
      "hr": 0,
      "bb": 1,
      "hbp": 0,
      "so": 0
    },
    {
      "batterId": "전주고_성민수_9",
      "pitcherId": "청주고_엄태현_31",
      "ab": 1,
      "h": 1,
      "b2": 0,
      "b3": 0,
      "hr": 0,
      "bb": 0,
      "hbp": 0,
      "so": 0
    },
    {
      "batterId": "전주고_성민수_9",
      "pitcherId": "청주고_손시우_46",
      "ab": 1,
      "h": 0,
      "b2": 0,
      "b3": 0,
      "hr": 0,
      "bb": 0,
      "hbp": 0,
      "so": 0
    },
    {
      "batterId": "전주고_성민수_9",
      "pitcherId": "청주고_강민준_55",
      "ab": 1,
      "h": 0,
      "b2": 0,
      "b3": 0,
      "hr": 0,
      "bb": 0,
      "hbp": 0,
      "so": 1
    },
    {
      "batterId": "전주고_정석주_8",
      "pitcherId": "청주고_한현우_47",
      "ab": 0,
      "h": 0,
      "b2": 0,
      "b3": 0,
      "hr": 0,
      "bb": 1,
      "hbp": 0,
      "so": 0
    },
    {
      "batterId": "전주고_김유빈_25",
      "pitcherId": "청주고_엄태현_31",
      "ab": 1,
      "h": 1,
      "b2": 1,
      "b3": 0,
      "hr": 0,
      "bb": 0,
      "hbp": 0,
      "so": 0
    },
    {
      "batterId": "전주고_김유빈_25",
      "pitcherId": "청주고_손시우_46",
      "ab": 0,
      "h": 0,
      "b2": 0,
      "b3": 0,
      "hr": 0,
      "bb": 0,
      "hbp": 1,
      "so": 0
    },
    {
      "batterId": "전주고_김유빈_25",
      "pitcherId": "청주고_강민준_55",
      "ab": 1,
      "h": 0,
      "b2": 0,
      "b3": 0,
      "hr": 0,
      "bb": 0,
      "hbp": 0,
      "so": 0
    },
    {
      "batterId": "전주고_송관우_15",
      "pitcherId": "청주고_한현우_47",
      "ab": 1,
      "h": 0,
      "b2": 0,
      "b3": 0,
      "hr": 0,
      "bb": 0,
      "hbp": 0,
      "so": 1
    },
    {
      "batterId": "전주고_윤도연_51",
      "pitcherId": "청주고_엄태현_31",
      "ab": 1,
      "h": 0,
      "b2": 0,
      "b3": 0,
      "hr": 0,
      "bb": 0,
      "hbp": 0,
      "so": 1
    },
    {
      "batterId": "전주고_윤도연_51",
      "pitcherId": "청주고_손시우_46",
      "ab": 0,
      "h": 0,
      "b2": 0,
      "b3": 0,
      "hr": 0,
      "bb": 0,
      "hbp": 1,
      "so": 0
    },
    {
      "batterId": "전주고_윤도연_51",
      "pitcherId": "청주고_강민준_55",
      "ab": 1,
      "h": 1,
      "b2": 0,
      "b3": 0,
      "hr": 0,
      "bb": 0,
      "hbp": 0,
      "so": 0
    },
    {
      "batterId": "전주고_윤도연_51",
      "pitcherId": "청주고_한현우_47",
      "ab": 1,
      "h": 1,
      "b2": 0,
      "b3": 0,
      "hr": 0,
      "bb": 0,
      "hbp": 0,
      "so": 0
    },
    {
      "batterId": "전주고_김서준_3",
      "pitcherId": "청주고_손시우_46",
      "ab": 2,
      "h": 0,
      "b2": 0,
      "b3": 0,
      "hr": 0,
      "bb": 0,
      "hbp": 0,
      "so": 1
    },
    {
      "batterId": "전주고_유재민_43",
      "pitcherId": "청주고_강민준_55",
      "ab": 1,
      "h": 1,
      "b2": 0,
      "b3": 0,
      "hr": 0,
      "bb": 0,
      "hbp": 0,
      "so": 0
    },
    {
      "batterId": "전주고_이호민_1",
      "pitcherId": "청주고_한현우_47",
      "ab": 1,
      "h": 1,
      "b2": 0,
      "b3": 0,
      "hr": 0,
      "bb": 0,
      "hbp": 0,
      "so": 0
    },
    {
      "batterId": "청주고_현빈_1",
      "pitcherId": "전주고_이호민_1",
      "ab": 2,
      "h": 0,
      "b2": 0,
      "b3": 0,
      "hr": 0,
      "bb": 0,
      "hbp": 0,
      "so": 0
    },
    {
      "batterId": "청주고_조백경_58",
      "pitcherId": "전주고_이호민_1",
      "ab": 2,
      "h": 0,
      "b2": 0,
      "b3": 0,
      "hr": 0,
      "bb": 0,
      "hbp": 0,
      "so": 1
    },
    {
      "batterId": "청주고_정제은_52",
      "pitcherId": "전주고_이호민_1",
      "ab": 2,
      "h": 1,
      "b2": 0,
      "b3": 0,
      "hr": 0,
      "bb": 0,
      "hbp": 0,
      "so": 0
    },
    {
      "batterId": "청주고_남관무_51",
      "pitcherId": "전주고_이호민_1",
      "ab": 2,
      "h": 0,
      "b2": 0,
      "b3": 0,
      "hr": 0,
      "bb": 0,
      "hbp": 0,
      "so": 0
    },
    {
      "batterId": "청주고_서승운_6",
      "pitcherId": "전주고_이호민_1",
      "ab": 1,
      "h": 0,
      "b2": 0,
      "b3": 0,
      "hr": 0,
      "bb": 0,
      "hbp": 0,
      "so": 0
    },
    {
      "batterId": "청주고_서승운_6",
      "pitcherId": "전주고_송관우_15",
      "ab": 1,
      "h": 0,
      "b2": 0,
      "b3": 0,
      "hr": 0,
      "bb": 0,
      "hbp": 0,
      "so": 0
    },
    {
      "batterId": "청주고_이주원_42",
      "pitcherId": "전주고_이호민_1",
      "ab": 1,
      "h": 0,
      "b2": 0,
      "b3": 0,
      "hr": 0,
      "bb": 0,
      "hbp": 0,
      "so": 1
    },
    {
      "batterId": "청주고_이주원_42",
      "pitcherId": "전주고_송관우_15",
      "ab": 1,
      "h": 1,
      "b2": 1,
      "b3": 0,
      "hr": 0,
      "bb": 0,
      "hbp": 0,
      "so": 0
    },
    {
      "batterId": "청주고_강동현_24",
      "pitcherId": "전주고_이호민_1",
      "ab": 1,
      "h": 0,
      "b2": 0,
      "b3": 0,
      "hr": 0,
      "bb": 0,
      "hbp": 0,
      "so": 0
    },
    {
      "batterId": "청주고_조이서_50",
      "pitcherId": "전주고_송관우_15",
      "ab": 1,
      "h": 0,
      "b2": 0,
      "b3": 0,
      "hr": 0,
      "bb": 0,
      "hbp": 0,
      "so": 0
    },
    {
      "batterId": "청주고_김학래_5",
      "pitcherId": "전주고_이호민_1",
      "ab": 1,
      "h": 0,
      "b2": 0,
      "b3": 0,
      "hr": 0,
      "bb": 0,
      "hbp": 0,
      "so": 0
    },
    {
      "batterId": "청주고_김학래_5",
      "pitcherId": "전주고_송관우_15",
      "ab": 1,
      "h": 0,
      "b2": 0,
      "b3": 0,
      "hr": 0,
      "bb": 0,
      "hbp": 0,
      "so": 0
    },
    {
      "batterId": "청주고_박종인_32",
      "pitcherId": "전주고_이호민_1",
      "ab": 1,
      "h": 0,
      "b2": 0,
      "b3": 0,
      "hr": 0,
      "bb": 0,
      "hbp": 0,
      "so": 1
    }
  ]
}
