{
  "id": "34430",
  "date": "2025-04-01",
  "season": 2025,
  "home": "서울동산",
  "away": "광주BC",
  "score": {
    "home": 10,
    "away": 1
  },
  "title": "2025 신세계 이마트배 전국고교야구대회",
  "batters": [
    {
      "playerId": "광주BC_안승찬_3",
      "name": "안승찬",
      "team": "광주BC",
      "ab": 3,
      "h": 1,
      "rbi": 0,
      "r": 0,
      "b2": 0,
      "b3": 0,
      "hr": 0,
      "bb": 0,
      "hbp": 0,
      "so": 0,
      "sb": 1
    },
    {
      "playerId": "광주BC_심도윤_25",
      "name": "심도윤",
      "team": "광주BC",
      "ab": 3,
      "h": 0,
      "rbi": 0,
      "r": 0,
      "b2": 0,
      "b3": 0,
      "hr": 0,
      "bb": 0,
      "hbp": 0,
      "so": 2,
      "sb": 0
    },
    {
      "playerId": "광주BC_안은찬_52",
      "name": "안은찬",
      "team": "광주BC",
      "ab": 2,
      "h": 0,
      "rbi": 0,
      "r": 0,
      "b2": 0,
      "b3": 0,
      "hr": 0,
      "bb": 1,
      "hbp": 0,
      "so": 1,
      "sb": 0
    },
    {
      "playerId": "광주BC_윤재연_5",
      "name": "윤재연",
      "team": "광주BC",
      "ab": 1,
      "h": 0,
      "rbi": 0,
      "r": 1,
      "b2": 0,
      "b3": 0,
      "hr": 0,
      "bb": 1,
      "hbp": 1,
      "so": 0,
      "sb": 0
    },
    {
      "playerId": "광주BC_이종휘_6",
      "name": "이종휘",
      "team": "광주BC",
      "ab": 1,
      "h": 0,
      "rbi": 0,
      "r": 0,
      "b2": 0,
      "b3": 0,
      "hr": 0,
      "bb": 0,
      "hbp": 0,
      "so": 1,
      "sb": 0
    },
    {
      "playerId": "광주BC_최용진_42",
      "name": "최용진",
      "team": "광주BC",
      "ab": 1,
      "h": 0,
      "rbi": 0,
      "r": 0,
      "b2": 0,
      "b3": 0,
      "hr": 0,
      "bb": 0,
      "hbp": 0,
      "so": 0,
      "sb": 0
    },
    {
      "playerId": "광주BC_송동현_16",
      "name": "송동현",
      "team": "광주BC",
      "ab": 2,
      "h": 0,
      "rbi": 0,
      "r": 0,
      "b2": 0,
      "b3": 0,
      "hr": 0,
      "bb": 1,
      "hbp": 0,
      "so": 1,
      "sb": 0
    },
    {
      "playerId": "광주BC_김기성_24",
      "name": "김기성",
      "team": "광주BC",
      "ab": 2,
      "h": 1,
      "rbi": 0,
      "r": 0,
      "b2": 0,
      "b3": 0,
      "hr": 0,
      "bb": 1,
      "hbp": 0,
      "so": 0,
      "sb": 0
    },
    {
      "playerId": "광주BC_이준명_12",
      "name": "이준명",
      "team": "광주BC",
      "ab": 3,
      "h": 0,
      "rbi": 0,
      "r": 0,
      "b2": 0,
      "b3": 0,
      "hr": 0,
      "bb": 0,
      "hbp": 0,
      "so": 2,
      "sb": 0
    },
    {
      "playerId": "광주BC_박승주_18",
      "name": "박승주",
      "team": "광주BC",
      "ab": 3,
      "h": 0,
      "rbi": 0,
      "r": 0,
      "b2": 0,
      "b3": 0,
      "hr": 0,
      "bb": 0,
      "hbp": 0,
      "so": 1,
      "sb": 0
    },
    {
      "playerId": "서울동산_김준호_7",
      "name": "김준호",
      "team": "서울동산",
      "ab": 4,
      "h": 2,
      "rbi": 1,
      "r": 2,
      "b2": 0,
      "b3": 0,
      "hr": 0,
      "bb": 0,
      "hbp": 0,
      "so": 0,
      "sb": 1
    },
    {
      "playerId": "서울동산_이영택_52",
      "name": "이영택",
      "team": "서울동산",
      "ab": 3,
      "h": 2,
      "rbi": 0,
      "r": 1,
      "b2": 0,
      "b3": 0,
      "hr": 0,
      "bb": 1,
      "hbp": 0,
      "so": 0,
      "sb": 2
    },
    {
      "playerId": "서울동산_박찬규_24",
      "name": "박찬규",
      "team": "서울동산",
      "ab": 4,
      "h": 2,
      "rbi": 0,
      "r": 2,
      "b2": 0,
      "b3": 0,
      "hr": 0,
      "bb": 0,
      "hbp": 0,
      "so": 1,
      "sb": 1
    },
    {
      "playerId": "서울동산_우태이_16",
      "name": "우태이",
      "team": "서울동산",
      "ab": 3,
      "h": 1,
      "rbi": 0,
      "r": 2,
      "b2": 0,
      "b3": 1,
      "hr": 0,
      "bb": 1,
      "hbp": 0,
      "so": 0,
      "sb": 0
    },
    {
      "playerId": "서울동산_채승민_47",
      "name": "채승민",
      "team": "서울동산",
      "ab": 2,
      "h": 1,
      "rbi": 1,
      "r": 0,
      "b2": 1,
      "b3": 0,
      "hr": 0,
      "bb": 0,
      "hbp": 2,
      "so": 0,
      "sb": 0
    },
    {
      "playerId": "서울동산_한유성_51",
      "name": "한유성",
      "team": "서울동산",
      "ab": 3,
      "h": 0,
      "rbi": 1,
      "r": 1,
      "b2": 0,
      "b3": 0,
      "hr": 0,
      "bb": 0,
      "hbp": 0,
      "so": 0,
      "sb": 0
    },
    {
      "playerId": "서울동산_배서준_10",
      "name": "배서준",
      "team": "서울동산",
      "ab": 1,
      "h": 1,
      "rbi": 2,
      "r": 0,
      "b2": 0,
      "b3": 0,
      "hr": 0,
      "bb": 0,
      "hbp": 0,
      "so": 0,
      "sb": 0
    },
    {
      "playerId": "서울동산_이연재_9",
      "name": "이연재",
      "team": "서울동산",
      "ab": 4,
      "h": 2,
      "rbi": 0,
      "r": 0,
      "b2": 0,
      "b3": 0,
      "hr": 0,
      "bb": 0,
      "hbp": 0,
      "so": 0,
      "sb": 0
    },
    {
      "playerId": "서울동산_전민석_41",
      "name": "전민석",
      "team": "서울동산",
      "ab": 4,
      "h": 2,
      "rbi": 1,
      "r": 1,
      "b2": 0,
      "b3": 0,
      "hr": 0,
      "bb": 0,
      "hbp": 0,
      "so": 0,
      "sb": 0
    },
    {
      "playerId": "서울동산_전동건_35",
      "name": "전동건",
      "team": "서울동산",
      "ab": 3,
      "h": 1,
      "rbi": 0,
      "r": 1,
      "b2": 0,
      "b3": 0,
      "hr": 0,
      "bb": 0,
      "hbp": 0,
      "so": 0,
      "sb": 0
    },
    {
      "playerId": "서울동산_이지용_49",
      "name": "이지용",
      "team": "서울동산",
      "ab": 0,
      "h": 0,
      "rbi": 0,
      "r": 0,
      "b2": 0,
      "b3": 0,
      "hr": 0,
      "bb": 0,
      "hbp": 0,
      "so": 0,
      "sb": 0
    }
  ],
  "pitchers": [
    {
      "playerId": "광주BC_박용준_1",
      "name": "박용준",
      "team": "광주BC",
      "outs": 11,
      "h": 10,
      "r": 6,
      "er": 4,
      "bb": 1,
      "so": 1,
      "w": 0,
      "l": 1,
      "sv": 0
    },
    {
      "playerId": "광주BC_안은찬_52",
      "name": "안은찬",
      "team": "광주BC",
      "outs": 6,
      "h": 2,
      "r": 3,
      "er": 2,
      "bb": 1,
      "so": 0,
      "w": 0,
      "l": 0,
      "sv": 0
    },
    {
      "playerId": "광주BC_나현서_11",
      "name": "나현서",
      "team": "광주BC",
      "outs": 1,
      "h": 2,
      "r": 1,
      "er": 1,
      "bb": 2,
      "so": 0,
      "w": 0,
      "l": 0,
      "sv": 0
    },
    {
      "playerId": "서울동산_임동현_15",
      "name": "임동현",
      "team": "서울동산",
      "outs": 9,
      "h": 2,
      "r": 1,
      "er": 0,
      "bb": 0,
      "so": 4,
      "w": 0,
      "l": 0,
      "sv": 0
    },
    {
      "playerId": "서울동산_김범주_21",
      "name": "김범주",
      "team": "서울동산",
      "outs": 9,
      "h": 0,
      "r": 0,
      "er": 0,
      "bb": 2,
      "so": 3,
      "w": 1,
      "l": 0,
      "sv": 0
    },
    {
      "playerId": "서울동산_서은철_12",
      "name": "서은철",
      "team": "서울동산",
      "outs": 1,
      "h": 0,
      "r": 0,
      "er": 0,
      "bb": 3,
      "so": 0,
      "w": 0,
      "l": 0,
      "sv": 0
    },
    {
      "playerId": "서울동산_하윤성_18",
      "name": "하윤성",
      "team": "서울동산",
      "outs": 2,
      "h": 0,
      "r": 0,
      "er": 0,
      "bb": 0,
      "so": 1,
      "w": 0,
      "l": 0,
      "sv": 0
    }
  ],
  "matchups": [
    {
      "batterId": "광주BC_안승찬_3",
      "pitcherId": "서울동산_임동현_15",
      "ab": 2,
      "h": 1,
      "b2": 0,
      "b3": 0,
      "hr": 0,
      "bb": 0,
      "hbp": 0,
      "so": 0
    },
    {
      "batterId": "광주BC_안승찬_3",
      "pitcherId": "서울동산_김범주_21",
      "ab": 1,
      "h": 0,
      "b2": 0,
      "b3": 0,
      "hr": 0,
      "bb": 0,
      "hbp": 0,
      "so": 0
    },
    {
      "batterId": "광주BC_심도윤_25",
      "pitcherId": "서울동산_임동현_15",
      "ab": 2,
      "h": 0,
      "b2": 0,
      "b3": 0,
      "hr": 0,
      "bb": 0,
      "hbp": 0,
      "so": 2
    },
    {
      "batterId": "광주BC_심도윤_25",
      "pitcherId": "서울동산_김범주_21",
      "ab": 1,
      "h": 0,
      "b2": 0,
      "b3": 0,
      "hr": 0,
      "bb": 0,
      "hbp": 0,
      "so": 0
    },
    {
      "batterId": "광주BC_안은찬_52",
      "pitcherId": "서울동산_임동현_15",
      "ab": 1,
      "h": 0,
      "b2": 0,
      "b3": 0,
      "hr": 0,
      "bb": 0,
      "hbp": 0,
      "so": 1
    },
    {
      "batterId": "광주BC_안은찬_52",
      "pitcherId": "서울동산_김범주_21",
      "ab": 1,
      "h": 0,
      "b2": 0,
      "b3": 0,
      "hr": 0,
      "bb": 1,
      "hbp": 0,
      "so": 0
    },
    {
      "batterId": "광주BC_윤재연_5",
      "pitcherId": "서울동산_임동현_15",
      "ab": 1,
      "h": 0,
      "b2": 0,
      "b3": 0,
      "hr": 0,
      "bb": 0,
      "hbp": 0,
      "so": 0
    },
    {
      "batterId": "광주BC_윤재연_5",
      "pitcherId": "서울동산_김범주_21",
      "ab": 0,
      "h": 0,
      "b2": 0,
      "b3": 0,
      "hr": 0,
      "bb": 0,
      "hbp": 1,
      "so": 0
    },
    {
      "batterId": "광주BC_윤재연_5",
      "pitcherId": "서울동산_서은철_12",
      "ab": 0,
      "h": 0,
      "b2": 0,
      "b3": 0,
      "hr": 0,
      "bb": 1,
      "hbp": 0,
      "so": 0
    },
    {
      "batterId": "광주BC_이종휘_6",
      "pitcherId": "서울동산_임동현_15",
      "ab": 1,
      "h": 0,
      "b2": 0,
      "b3": 0,
      "hr": 0,
      "bb": 0,
      "hbp": 0,
      "so": 0
    },
    {
      "batterId": "광주BC_이종휘_6",
      "pitcherId": "서울동산_김범주_21",
      "ab": 1,
      "h": 0,
      "b2": 0,
      "b3": 0,
      "hr": 0,
      "bb": 0,
      "hbp": 0,
      "so": 1
    },
    {
      "batterId": "광주BC_최용진_42",
      "pitcherId": "서울동산_서은철_12",
      "ab": 1,
      "h": 0,
      "b2": 0,
      "b3": 0,
      "hr": 0,
      "bb": 0,
      "hbp": 0,
      "so": 0
    },
    {
      "batterId": "광주BC_송동현_16",
      "pitcherId": "서울동산_임동현_15",
      "ab": 1,
      "h": 0,
      "b2": 0,
      "b3": 0,
      "hr": 0,
      "bb": 0,
      "hbp": 0,
      "so": 1
    },
    {
      "batterId": "광주BC_송동현_16",
      "pitcherId": "서울동산_김범주_21",
      "ab": 1,
      "h": 0,
      "b2": 0,
      "b3": 0,
      "hr": 0,
      "bb": 0,
      "hbp": 0,
      "so": 0
    },
    {
      "batterId": "광주BC_송동현_16",
      "pitcherId": "서울동산_서은철_12",
      "ab": 0,
      "h": 0,
      "b2": 0,
      "b3": 0,
      "hr": 0,
      "bb": 1,
      "hbp": 0,
      "so": 0
    },
    {
      "batterId": "광주BC_김기성_24",
      "pitcherId": "서울동산_임동현_15",
      "ab": 1,
      "h": 1,
      "b2": 0,
      "b3": 0,
      "hr": 0,
      "bb": 0,
      "hbp": 0,
      "so": 0
    },
    {
      "batterId": "광주BC_김기성_24",
      "pitcherId": "서울동산_김범주_21",
      "ab": 1,
      "h": 0,
      "b2": 0,
      "b3": 0,
      "hr": 0,
      "bb": 0,
      "hbp": 0,
      "so": 0
    },
    {
      "batterId": "광주BC_김기성_24",
      "pitcherId": "서울동산_서은철_12",
      "ab": 0,
      "h": 0,
      "b2": 0,
      "b3": 0,
      "hr": 0,
      "bb": 1,
      "hbp": 0,
      "so": 0
    },
    {
      "batterId": "광주BC_이준명_12",
      "pitcherId": "서울동산_임동현_15",
      "ab": 1,
      "h": 0,
      "b2": 0,
      "b3": 0,
      "hr": 0,
      "bb": 0,
      "hbp": 0,
      "so": 0
    },
    {
      "batterId": "광주BC_이준명_12",
      "pitcherId": "서울동산_김범주_21",
      "ab": 1,
      "h": 0,
      "b2": 0,
      "b3": 0,
      "hr": 0,
      "bb": 0,
      "hbp": 0,
      "so": 1
    },
    {
      "batterId": "광주BC_이준명_12",
      "pitcherId": "서울동산_서은철_12",
      "ab": 1,
      "h": 0,
      "b2": 0,
      "b3": 0,
      "hr": 0,
      "bb": 0,
      "hbp": 0,
      "so": 1
    },
    {
      "batterId": "광주BC_박승주_18",
      "pitcherId": "서울동산_임동현_15",
      "ab": 1,
      "h": 0,
      "b2": 0,
      "b3": 0,
      "hr": 0,
      "bb": 0,
      "hbp": 0,
      "so": 0
    },
    {
      "batterId": "광주BC_박승주_18",
      "pitcherId": "서울동산_김범주_21",
      "ab": 1,
      "h": 0,
      "b2": 0,
      "b3": 0,
      "hr": 0,
      "bb": 0,
      "hbp": 0,
      "so": 1
    },
    {
      "batterId": "광주BC_박승주_18",
      "pitcherId": "서울동산_서은철_12",
      "ab": 1,
      "h": 0,
      "b2": 0,
      "b3": 0,
      "hr": 0,
      "bb": 0,
      "hbp": 0,
      "so": 0
    },
    {
      "batterId": "서울동산_김준호_7",
      "pitcherId": "광주BC_박용준_1",
      "ab": 3,
      "h": 1,
      "b2": 0,
      "b3": 0,
      "hr": 0,
      "bb": 0,
      "hbp": 0,
      "so": 0
    },
    {
      "batterId": "서울동산_김준호_7",
      "pitcherId": "광주BC_안은찬_52",
      "ab": 1,
      "h": 1,
      "b2": 0,
      "b3": 0,
      "hr": 0,
      "bb": 0,
      "hbp": 0,
      "so": 0
    },
    {
      "batterId": "서울동산_이영택_52",
      "pitcherId": "광주BC_박용준_1",
      "ab": 3,
      "h": 2,
      "b2": 0,
      "b3": 0,
      "hr": 0,
      "bb": 0,
      "hbp": 0,
      "so": 0
    },
    {
      "batterId": "서울동산_이영택_52",
      "pitcherId": "광주BC_안은찬_52",
      "ab": 0,
      "h": 0,
      "b2": 0,
      "b3": 0,
      "hr": 0,
      "bb": 1,
      "hbp": 0,
      "so": 0
    },
    {
      "batterId": "서울동산_박찬규_24",
      "pitcherId": "광주BC_박용준_1",
      "ab": 3,
      "h": 1,
      "b2": 0,
      "b3": 0,
      "hr": 0,
      "bb": 0,
      "hbp": 0,
      "so": 1
    },
    {
      "batterId": "서울동산_박찬규_24",
      "pitcherId": "광주BC_안은찬_52",
      "ab": 1,
      "h": 1,
      "b2": 0,
      "b3": 0,
      "hr": 0,
      "bb": 0,
      "hbp": 0,
      "so": 0
    },
    {
      "batterId": "서울동산_우태이_16",
      "pitcherId": "광주BC_박용준_1",
      "ab": 3,
      "h": 1,
      "b2": 0,
      "b3": 1,
      "hr": 0,
      "bb": 0,
      "hbp": 0,
      "so": 0
    },
    {
      "batterId": "서울동산_우태이_16",
      "pitcherId": "광주BC_안은찬_52",
      "ab": 0,
      "h": 0,
      "b2": 0,
      "b3": 0,
      "hr": 0,
      "bb": 1,
      "hbp": 0,
      "so": 0
    },
    {
      "batterId": "서울동산_채승민_47",
      "pitcherId": "광주BC_박용준_1",
      "ab": 1,
      "h": 1,
      "b2": 1,
      "b3": 0,
      "hr": 0,
      "bb": 0,
      "hbp": 1,
      "so": 0
    },
    {
      "batterId": "서울동산_채승민_47",
      "pitcherId": "광주BC_안은찬_52",
      "ab": 1,
      "h": 0,
      "b2": 0,
      "b3": 0,
      "hr": 0,
      "bb": 0,
      "hbp": 1,
      "so": 0
    },
    {
      "batterId": "서울동산_한유성_51",
      "pitcherId": "광주BC_박용준_1",
      "ab": 2,
      "h": 0,
      "b2": 0,
      "b3": 0,
      "hr": 0,
      "bb": 0,
      "hbp": 0,
      "so": 0
    },
    {
      "batterId": "서울동산_한유성_51",
      "pitcherId": "광주BC_안은찬_52",
      "ab": 1,
      "h": 0,
      "b2": 0,
      "b3": 0,
      "hr": 0,
      "bb": 0,
      "hbp": 0,
      "so": 0
    },
    {
      "batterId": "서울동산_배서준_10",
      "pitcherId": "광주BC_안은찬_52",
      "ab": 1,
      "h": 1,
      "b2": 0,
      "b3": 0,
      "hr": 0,
      "bb": 0,
      "hbp": 0,
      "so": 0
    },
    {
      "batterId": "서울동산_이연재_9",
      "pitcherId": "광주BC_박용준_1",
      "ab": 2,
      "h": 1,
      "b2": 0,
      "b3": 0,
      "hr": 0,
      "bb": 0,
      "hbp": 0,
      "so": 0
    },
    {
      "batterId": "서울동산_이연재_9",
      "pitcherId": "광주BC_안은찬_52",
      "ab": 2,
      "h": 1,
      "b2": 0,
      "b3": 0,
      "hr": 0,
      "bb": 0,
      "hbp": 0,
      "so": 0
    },
    {
      "batterId": "서울동산_전민석_41",
      "pitcherId": "광주BC_박용준_1",
      "ab": 2,
      "h": 2,
      "b2": 0,
      "b3": 0,
      "hr": 0,
      "bb": 0,
      "hbp": 0,
      "so": 0
    },
    {
      "batterId": "서울동산_전민석_41",
      "pitcherId": "광주BC_안은찬_52",
      "ab": 1,
      "h": 0,
      "b2": 0,
      "b3": 0,
      "hr": 0,
      "bb": 0,
      "hbp": 0,
      "so": 0
    },
    {
      "batterId": "서울동산_전동건_35",
      "pitcherId": "광주BC_박용준_1",
      "ab": 2,
      "h": 1,
      "b2": 0,
      "b3": 0,
      "hr": 0,
      "bb": 0,
      "hbp": 0,
      "so": 0
    },
    {
      "batterId": "서울동산_전동건_35",
      "pitcherId": "광주BC_안은찬_52",
      "ab": 1,
      "h": 0,
      "b2": 0,
      "b3": 0,
      "hr": 0,
      "bb": 0,
      "hbp": 0,
      "so": 0
    }
  ]
}
