{
  "id": "36094",
  "date": "2025-08-18",
  "season": 2025,
  "home": "야로고BC",
  "away": "물금고",
  "score": {
    "home": 1,
    "away": 4
  },
  "title": "제53회 봉황대기 전국고교야구대회",
  "batters": [
    {
      "playerId": "물금고_양재목_50",
      "name": "양재목",
      "team": "물금고",
      "ab": 4,
      "h": 1,
      "rbi": 0,
      "r": 1,
      "b2": 0,
      "b3": 0,
      "hr": 0,
      "bb": 1,
      "hbp": 0,
      "so": 0,
      "sb": 1
    },
    {
      "playerId": "물금고_오지운_15",
      "name": "오지운",
      "team": "물금고",
      "ab": 4,
      "h": 0,
      "rbi": 0,
      "r": 0,
      "b2": 0,
      "b3": 0,
      "hr": 0,
      "bb": 0,
      "hbp": 0,
      "so": 2,
      "sb": 0
    },
    {
      "playerId": "물금고_이재환_1",
      "name": "이재환",
      "team": "물금고",
      "ab": 4,
      "h": 1,
      "rbi": 0,
      "r": 0,
      "b2": 0,
      "b3": 0,
      "hr": 0,
      "bb": 1,
      "hbp": 0,
      "so": 0,
      "sb": 3
    },
    {
      "playerId": "물금고_김기환_23",
      "name": "김기환",
      "team": "물금고",
      "ab": 3,
      "h": 0,
      "rbi": 0,
      "r": 1,
      "b2": 0,
      "b3": 0,
      "hr": 0,
      "bb": 1,
      "hbp": 0,
      "so": 1,
      "sb": 0
    },
    {
      "playerId": "물금고_박현준_16",
      "name": "박현준",
      "team": "물금고",
      "ab": 3,
      "h": 2,
      "rbi": 2,
      "r": 2,
      "b2": 1,
      "b3": 0,
      "hr": 1,
      "bb": 0,
      "hbp": 1,
      "so": 1,
      "sb": 0
    },
    {
      "playerId": "물금고_윤지유_2",
      "name": "윤지유",
      "team": "물금고",
      "ab": 3,
      "h": 1,
      "rbi": 0,
      "r": 0,
      "b2": 0,
      "b3": 0,
      "hr": 0,
      "bb": 1,
      "hbp": 0,
      "so": 1,
      "sb": 0
    },
    {
      "playerId": "물금고_노진모_27",
      "name": "노진모",
      "team": "물금고",
      "ab": 3,
      "h": 0,
      "rbi": 0,
      "r": 0,
      "b2": 0,
      "b3": 0,
      "hr": 0,
      "bb": 0,
      "hbp": 0,
      "so": 0,
      "sb": 0
    },
    {
      "playerId": "물금고_김준우_5",
      "name": "김준우",
      "team": "물금고",
      "ab": 3,
      "h": 1,
      "rbi": 0,
      "r": 0,
      "b2": 0,
      "b3": 0,
      "hr": 0,
      "bb": 0,
      "hbp": 0,
      "so": 0,
      "sb": 0
    },
    {
      "playerId": "물금고_임종헌_13",
      "name": "임종헌",
      "team": "물금고",
      "ab": 0,
      "h": 0,
      "rbi": 0,
      "r": 0,
      "b2": 0,
      "b3": 0,
      "hr": 0,
      "bb": 0,
      "hbp": 0,
      "so": 0,
      "sb": 0
    },
    {
      "playerId": "물금고_예은찬_3",
      "name": "예은찬",
      "team": "물금고",
      "ab": 0,
      "h": 0,
      "rbi": 0,
      "r": 0,
      "b2": 0,
      "b3": 0,
      "hr": 0,
      "bb": 0,
      "hbp": 0,
      "so": 0,
      "sb": 0
    },
    {
      "playerId": "물금고_김우린_10",
      "name": "김우린",
      "team": "물금고",
      "ab": 0,
      "h": 0,
      "rbi": 0,
      "r": 0,
      "b2": 0,
      "b3": 0,
      "hr": 0,
      "bb": 1,
      "hbp": 0,
      "so": 0,
      "sb": 1
    },
    {
      "playerId": "물금고_현지호_53",
      "name": "현지호",
      "team": "물금고",
      "ab": 4,
      "h": 1,
      "rbi": 0,
      "r": 0,
      "b2": 0,
      "b3": 0,
      "hr": 0,
      "bb": 0,
      "hbp": 0,
      "so": 1,
      "sb": 0
    },
    {
      "playerId": "야로고BC_김진우_7",
      "name": "김진우",
      "team": "야로고BC",
      "ab": 4,
      "h": 1,
      "rbi": 1,
      "r": 0,
      "b2": 0,
      "b3": 0,
      "hr": 0,
      "bb": 0,
      "hbp": 0,
      "so": 0,
      "sb": 0
    },
    {
      "playerId": "야로고BC_김민승_16",
      "name": "김민승",
      "team": "야로고BC",
      "ab": 4,
      "h": 2,
      "rbi": 0,
      "r": 0,
      "b2": 0,
      "b3": 0,
      "hr": 0,
      "bb": 0,
      "hbp": 0,
      "so": 0,
      "sb": 0
    },
    {
      "playerId": "야로고BC_임성준_6",
      "name": "임성준",
      "team": "야로고BC",
      "ab": 4,
      "h": 1,
      "rbi": 0,
      "r": 0,
      "b2": 0,
      "b3": 0,
      "hr": 0,
      "bb": 0,
      "hbp": 0,
      "so": 1,
      "sb": 0
    },
    {
      "playerId": "야로고BC_이주안_5",
      "name": "이주안",
      "team": "야로고BC",
      "ab": 4,
      "h": 1,
      "rbi": 0,
      "r": 0,
      "b2": 0,
      "b3": 0,
      "hr": 0,
      "bb": 0,
      "hbp": 0,
      "so": 1,
      "sb": 0
    },
    {
      "playerId": "야로고BC_전세운_15",
      "name": "전세운",
      "team": "야로고BC",
      "ab": 4,
      "h": 0,
      "rbi": 0,
      "r": 0,
      "b2": 0,
      "b3": 0,
      "hr": 0,
      "bb": 0,
      "hbp": 0,
      "so": 1,
      "sb": 0
    },
    {
      "playerId": "야로고BC_홍성현_27",
      "name": "홍성현",
      "team": "야로고BC",
      "ab": 2,
      "h": 0,
      "rbi": 0,
      "r": 0,
      "b2": 0,
      "b3": 0,
      "hr": 0,
      "bb": 2,
      "hbp": 0,
      "so": 1,
      "sb": 0
    },
    {
      "playerId": "야로고BC_최성빈_36",
      "name": "최성빈",
      "team": "야로고BC",
      "ab": 4,
      "h": 0,
      "rbi": 0,
      "r": 1,
      "b2": 0,
      "b3": 0,
      "hr": 0,
      "bb": 0,
      "hbp": 0,
      "so": 1,
      "sb": 0
    },
    {
      "playerId": "야로고BC_장준현_17",
      "name": "장준현",
      "team": "야로고BC",
      "ab": 3,
      "h": 0,
      "rbi": 0,
      "r": 0,
      "b2": 0,
      "b3": 0,
      "hr": 0,
      "bb": 1,
      "hbp": 0,
      "so": 1,
      "sb": 0
    },
    {
      "playerId": "야로고BC_이호선_9",
      "name": "이호선",
      "team": "야로고BC",
      "ab": 2,
      "h": 0,
      "rbi": 0,
      "r": 0,
      "b2": 0,
      "b3": 0,
      "hr": 0,
      "bb": 0,
      "hbp": 0,
      "so": 2,
      "sb": 0
    },
    {
      "playerId": "야로고BC_이정훈_22",
      "name": "이정훈",
      "team": "야로고BC",
      "ab": 2,
      "h": 0,
      "rbi": 0,
      "r": 0,
      "b2": 0,
      "b3": 0,
      "hr": 0,
      "bb": 0,
      "hbp": 0,
      "so": 0,
      "sb": 0
    }
  ],
  "pitchers": [
    {
      "playerId": "물금고_김태현_11",
      "name": "김태현",
      "team": "물금고",
      "outs": 5,
      "h": 3,
      "r": 1,
      "er": 1,
      "bb": 2,
      "so": 1,
      "w": 0,
      "l": 0,
      "sv": 0
    },
    {
      "playerId": "물금고_김진석_49",
      "name": "김진석",
      "team": "물금고",
      "outs": 14,
      "h": 0,
      "r": 0,
      "er": 0,
      "bb": 1,
      "so": 5,
      "w": 1,
      "l": 0,
      "sv": 0
    },
    {
      "playerId": "물금고_김준영_17",
      "name": "김준영",
      "team": "물금고",
      "outs": 8,
      "h": 2,
      "r": 0,
      "er": 0,
      "bb": 0,
      "so": 3,
      "w": 0,
      "l": 0,
      "sv": 0
    },
    {
      "playerId": "야로고BC_서도현_18",
      "name": "서도현",
      "team": "야로고BC",
      "outs": 9,
      "h": 2,
      "r": 4,
      "er": 4,
      "bb": 5,
      "so": 2,
      "w": 0,
      "l": 1,
      "sv": 0
    },
    {
      "playerId": "야로고BC_안상국_1",
      "name": "안상국",
      "team": "야로고BC",
      "outs": 8,
      "h": 4,
      "r": 0,
      "er": 0,
      "bb": 0,
      "so": 2,
      "w": 0,
      "l": 0,
      "sv": 0
    },
    {
      "playerId": "야로고BC_김용은_11",
      "name": "김용은",
      "team": "야로고BC",
      "outs": 7,
      "h": 1,
      "r": 0,
      "er": 0,
      "bb": 1,
      "so": 3,
      "w": 0,
      "l": 0,
      "sv": 0
    },
    {
      "playerId": "야로고BC_유다한_19",
      "name": "유다한",
      "team": "야로고BC",
      "outs": 2,
      "h": 0,
      "r": 0,
      "er": 0,
      "bb": 0,
      "so": 1,
      "w": 0,
      "l": 0,
      "sv": 0
    },
    {
      "playerId": "야로고BC_이서진_32",
      "name": "이서진",
      "team": "야로고BC",
      "outs": 1,
      "h": 0,
      "r": 0,
      "er": 0,
      "bb": 0,
      "so": 0,
      "w": 0,
      "l": 0,
      "sv": 0
    }
  ],
  "matchups": [
    {
      "batterId": "물금고_양재목_50",
      "pitcherId": "야로고BC_서도현_18",
      "ab": 1,
      "h": 0,
      "b2": 0,
      "b3": 0,
      "hr": 0,
      "bb": 1,
      "hbp": 0,
      "so": 0
    },
    {
      "batterId": "물금고_양재목_50",
      "pitcherId": "야로고BC_안상국_1",
      "ab": 2,
      "h": 1,
      "b2": 0,
      "b3": 0,
      "hr": 0,
      "bb": 0,
      "hbp": 0,
      "so": 0
    },
    {
      "batterId": "물금고_양재목_50",
      "pitcherId": "야로고BC_유다한_19",
      "ab": 1,
      "h": 0,
      "b2": 0,
      "b3": 0,
      "hr": 0,
      "bb": 0,
      "hbp": 0,
      "so": 0
    },
    {
      "batterId": "물금고_오지운_15",
      "pitcherId": "야로고BC_서도현_18",
      "ab": 2,
      "h": 0,
      "b2": 0,
      "b3": 0,
      "hr": 0,
      "bb": 0,
      "hbp": 0,
      "so": 0
    },
    {
      "batterId": "물금고_오지운_15",
      "pitcherId": "야로고BC_안상국_1",
      "ab": 1,
      "h": 0,
      "b2": 0,
      "b3": 0,
      "hr": 0,
      "bb": 0,
      "hbp": 0,
      "so": 0
    },
    {
      "batterId": "물금고_오지운_15",
      "pitcherId": "야로고BC_김용은_11",
      "ab": 1,
      "h": 0,
      "b2": 0,
      "b3": 0,
      "hr": 0,
      "bb": 0,
      "hbp": 0,
      "so": 1
    },
    {
      "batterId": "물금고_오지운_15",
      "pitcherId": "야로고BC_유다한_19",
      "ab": 1,
      "h": 0,
      "b2": 0,
      "b3": 0,
      "hr": 0,
      "bb": 0,
      "hbp": 0,
      "so": 1
    },
    {
      "batterId": "물금고_이재환_1",
      "pitcherId": "야로고BC_서도현_18",
      "ab": 1,
      "h": 0,
      "b2": 0,
      "b3": 0,
      "hr": 0,
      "bb": 1,
      "hbp": 0,
      "so": 0
    },
    {
      "batterId": "물금고_이재환_1",
      "pitcherId": "야로고BC_안상국_1",
      "ab": 1,
      "h": 1,
      "b2": 0,
      "b3": 0,
      "hr": 0,
      "bb": 0,
      "hbp": 0,
      "so": 0
    },
    {
      "batterId": "물금고_이재환_1",
      "pitcherId": "야로고BC_김용은_11",
      "ab": 1,
      "h": 0,
      "b2": 0,
      "b3": 0,
      "hr": 0,
      "bb": 0,
      "hbp": 0,
      "so": 0
    },
    {
      "batterId": "물금고_이재환_1",
      "pitcherId": "야로고BC_유다한_19",
      "ab": 1,
      "h": 0,
      "b2": 0,
      "b3": 0,
      "hr": 0,
      "bb": 0,
      "hbp": 0,
      "so": 0
    },
    {
      "batterId": "물금고_김기환_23",
      "pitcherId": "야로고BC_서도현_18",
      "ab": 1,
      "h": 0,
      "b2": 0,
      "b3": 0,
      "hr": 0,
      "bb": 1,
      "hbp": 0,
      "so": 0
    },
    {
      "batterId": "물금고_김기환_23",
      "pitcherId": "야로고BC_안상국_1",
      "ab": 1,
      "h": 0,
      "b2": 0,
      "b3": 0,
      "hr": 0,
      "bb": 0,
      "hbp": 0,
      "so": 0
    },
    {
      "batterId": "물금고_김기환_23",
      "pitcherId": "야로고BC_김용은_11",
      "ab": 1,
      "h": 0,
      "b2": 0,
      "b3": 0,
      "hr": 0,
      "bb": 0,
      "hbp": 0,
      "so": 1
    },
    {
      "batterId": "물금고_박현준_16",
      "pitcherId": "야로고BC_서도현_18",
      "ab": 1,
      "h": 1,
      "b2": 0,
      "b3": 0,
      "hr": 1,
      "bb": 0,
      "hbp": 1,
      "so": 0
    },
    {
      "batterId": "물금고_박현준_16",
      "pitcherId": "야로고BC_안상국_1",
      "ab": 1,
      "h": 0,
      "b2": 0,
      "b3": 0,
      "hr": 0,
      "bb": 0,
      "hbp": 0,
      "so": 1
    },
    {
      "batterId": "물금고_박현준_16",
      "pitcherId": "야로고BC_김용은_11",
      "ab": 1,
      "h": 1,
      "b2": 1,
      "b3": 0,
      "hr": 0,
      "bb": 0,
      "hbp": 0,
      "so": 0
    },
    {
      "batterId": "물금고_윤지유_2",
      "pitcherId": "야로고BC_서도현_18",
      "ab": 1,
      "h": 1,
      "b2": 0,
      "b3": 0,
      "hr": 0,
      "bb": 1,
      "hbp": 0,
      "so": 0
    },
    {
      "batterId": "물금고_윤지유_2",
      "pitcherId": "야로고BC_안상국_1",
      "ab": 1,
      "h": 0,
      "b2": 0,
      "b3": 0,
      "hr": 0,
      "bb": 0,
      "hbp": 0,
      "so": 0
    },
    {
      "batterId": "물금고_윤지유_2",
      "pitcherId": "야로고BC_김용은_11",
      "ab": 1,
      "h": 0,
      "b2": 0,
      "b3": 0,
      "hr": 0,
      "bb": 0,
      "hbp": 0,
      "so": 1
    },
    {
      "batterId": "물금고_노진모_27",
      "pitcherId": "야로고BC_서도현_18",
      "ab": 2,
      "h": 0,
      "b2": 0,
      "b3": 0,
      "hr": 0,
      "bb": 0,
      "hbp": 0,
      "so": 0
    },
    {
      "batterId": "물금고_노진모_27",
      "pitcherId": "야로고BC_안상국_1",
      "ab": 1,
      "h": 0,
      "b2": 0,
      "b3": 0,
      "hr": 0,
      "bb": 0,
      "hbp": 0,
      "so": 0
    },
    {
      "batterId": "물금고_노진모_27",
      "pitcherId": "야로고BC_김용은_11",
      "ab": 1,
      "h": 0,
      "b2": 0,
      "b3": 0,
      "hr": 0,
      "bb": 0,
      "hbp": 0,
      "so": 0
    },
    {
      "batterId": "물금고_김준우_5",
      "pitcherId": "야로고BC_서도현_18",
      "ab": 1,
      "h": 0,
      "b2": 0,
      "b3": 0,
      "hr": 0,
      "bb": 0,
      "hbp": 0,
      "so": 0
    },
    {
      "batterId": "물금고_김준우_5",
      "pitcherId": "야로고BC_안상국_1",
      "ab": 2,
      "h": 1,
      "b2": 0,
      "b3": 0,
      "hr": 0,
      "bb": 0,
      "hbp": 0,
      "so": 0
    },
    {
      "batterId": "물금고_임종헌_13",
      "pitcherId": "야로고BC_안상국_1",
      "ab": 1,
      "h": 0,
      "b2": 0,
      "b3": 0,
      "hr": 0,
      "bb": 0,
      "hbp": 0,
      "so": 0
    },
    {
      "batterId": "물금고_김우린_10",
      "pitcherId": "야로고BC_김용은_11",
      "ab": 0,
      "h": 0,
      "b2": 0,
      "b3": 0,
      "hr": 0,
      "bb": 1,
      "hbp": 0,
      "so": 0
    },
    {
      "batterId": "물금고_현지호_53",
      "pitcherId": "야로고BC_서도현_18",
      "ab": 1,
      "h": 0,
      "b2": 0,
      "b3": 0,
      "hr": 0,
      "bb": 0,
      "hbp": 0,
      "so": 1
    },
    {
      "batterId": "물금고_현지호_53",
      "pitcherId": "야로고BC_안상국_1",
      "ab": 2,
      "h": 1,
      "b2": 0,
      "b3": 0,
      "hr": 0,
      "bb": 0,
      "hbp": 0,
      "so": 0
    },
    {
      "batterId": "물금고_현지호_53",
      "pitcherId": "야로고BC_김용은_11",
      "ab": 1,
      "h": 0,
      "b2": 0,
      "b3": 0,
      "hr": 0,
      "bb": 0,
      "hbp": 0,
      "so": 0
    },
    {
      "batterId": "야로고BC_김진우_7",
      "pitcherId": "물금고_김태현_11",
      "ab": 2,
      "h": 1,
      "b2": 0,
      "b3": 0,
      "hr": 0,
      "bb": 0,
      "hbp": 0,
      "so": 0
    },
    {
      "batterId": "야로고BC_김진우_7",
      "pitcherId": "물금고_김진석_49",
      "ab": 2,
      "h": 0,
      "b2": 0,
      "b3": 0,
      "hr": 0,
      "bb": 0,
      "hbp": 0,
      "so": 0
    },
    {
      "batterId": "야로고BC_김민승_16",
      "pitcherId": "물금고_김태현_11",
      "ab": 2,
      "h": 1,
      "b2": 0,
      "b3": 0,
      "hr": 0,
      "bb": 0,
      "hbp": 0,
      "so": 0
    },
    {
      "batterId": "야로고BC_김민승_16",
      "pitcherId": "물금고_김진석_49",
      "ab": 1,
      "h": 0,
      "b2": 0,
      "b3": 0,
      "hr": 0,
      "bb": 0,
      "hbp": 0,
      "so": 0
    },
    {
      "batterId": "야로고BC_김민승_16",
      "pitcherId": "물금고_김준영_17",
      "ab": 1,
      "h": 1,
      "b2": 0,
      "b3": 0,
      "hr": 0,
      "bb": 0,
      "hbp": 0,
      "so": 0
    },
    {
      "batterId": "야로고BC_임성준_6",
      "pitcherId": "물금고_김태현_11",
      "ab": 1,
      "h": 0,
      "b2": 0,
      "b3": 0,
      "hr": 0,
      "bb": 0,
      "hbp": 0,
      "so": 0
    },
    {
      "batterId": "야로고BC_임성준_6",
      "pitcherId": "물금고_김진석_49",
      "ab": 2,
      "h": 0,
      "b2": 0,
      "b3": 0,
      "hr": 0,
      "bb": 0,
      "hbp": 0,
      "so": 1
    },
    {
      "batterId": "야로고BC_임성준_6",
      "pitcherId": "물금고_김준영_17",
      "ab": 1,
      "h": 1,
      "b2": 0,
      "b3": 0,
      "hr": 0,
      "bb": 0,
      "hbp": 0,
      "so": 0
    },
    {
      "batterId": "야로고BC_이주안_5",
      "pitcherId": "물금고_김태현_11",
      "ab": 1,
      "h": 1,
      "b2": 0,
      "b3": 0,
      "hr": 0,
      "bb": 0,
      "hbp": 0,
      "so": 0
    },
    {
      "batterId": "야로고BC_이주안_5",
      "pitcherId": "물금고_김진석_49",
      "ab": 2,
      "h": 0,
      "b2": 0,
      "b3": 0,
      "hr": 0,
      "bb": 0,
      "hbp": 0,
      "so": 1
    },
    {
      "batterId": "야로고BC_이주안_5",
      "pitcherId": "물금고_김준영_17",
      "ab": 1,
      "h": 0,
      "b2": 0,
      "b3": 0,
      "hr": 0,
      "bb": 0,
      "hbp": 0,
      "so": 0
    },
    {
      "batterId": "야로고BC_전세운_15",
      "pitcherId": "물금고_김태현_11",
      "ab": 1,
      "h": 0,
      "b2": 0,
      "b3": 0,
      "hr": 0,
      "bb": 0,
      "hbp": 0,
      "so": 0
    },
    {
      "batterId": "야로고BC_전세운_15",
      "pitcherId": "물금고_김진석_49",
      "ab": 2,
      "h": 0,
      "b2": 0,
      "b3": 0,
      "hr": 0,
      "bb": 0,
      "hbp": 0,
      "so": 1
    },
    {
      "batterId": "야로고BC_전세운_15",
      "pitcherId": "물금고_김준영_17",
      "ab": 1,
      "h": 0,
      "b2": 0,
      "b3": 0,
      "hr": 0,
      "bb": 0,
      "hbp": 0,
      "so": 0
    },
    {
      "batterId": "야로고BC_홍성현_27",
      "pitcherId": "물금고_김태현_11",
      "ab": 0,
      "h": 0,
      "b2": 0,
      "b3": 0,
      "hr": 0,
      "bb": 1,
      "hbp": 0,
      "so": 0
    },
    {
      "batterId": "야로고BC_홍성현_27",
      "pitcherId": "물금고_김진석_49",
      "ab": 1,
      "h": 0,
      "b2": 0,
      "b3": 0,
      "hr": 0,
      "bb": 1,
      "hbp": 0,
      "so": 0
    },
    {
      "batterId": "야로고BC_홍성현_27",
      "pitcherId": "물금고_김준영_17",
      "ab": 1,
      "h": 0,
      "b2": 0,
      "b3": 0,
      "hr": 0,
      "bb": 0,
      "hbp": 0,
      "so": 1
    },
    {
      "batterId": "야로고BC_최성빈_36",
      "pitcherId": "물금고_김태현_11",
      "ab": 1,
      "h": 0,
      "b2": 0,
      "b3": 0,
      "hr": 0,
      "bb": 0,
      "hbp": 0,
      "so": 0
    },
    {
      "batterId": "야로고BC_최성빈_36",
      "pitcherId": "물금고_김진석_49",
      "ab": 2,
      "h": 0,
      "b2": 0,
      "b3": 0,
      "hr": 0,
      "bb": 0,
      "hbp": 0,
      "so": 0
    },
    {
      "batterId": "야로고BC_최성빈_36",
      "pitcherId": "물금고_김준영_17",
      "ab": 1,
      "h": 0,
      "b2": 0,
      "b3": 0,
      "hr": 0,
      "bb": 0,
      "hbp": 0,
      "so": 1
    },
    {
      "batterId": "야로고BC_장준현_17",
      "pitcherId": "물금고_김태현_11",
      "ab": 0,
      "h": 0,
      "b2": 0,
      "b3": 0,
      "hr": 0,
      "bb": 1,
      "hbp": 0,
      "so": 0
    },
    {
      "batterId": "야로고BC_장준현_17",
      "pitcherId": "물금고_김진석_49",
      "ab": 2,
      "h": 0,
      "b2": 0,
      "b3": 0,
      "hr": 0,
      "bb": 0,
      "hbp": 0,
      "so": 1
    },
    {
      "batterId": "야로고BC_장준현_17",
      "pitcherId": "물금고_김준영_17",
      "ab": 1,
      "h": 0,
      "b2": 0,
      "b3": 0,
      "hr": 0,
      "bb": 0,
      "hbp": 0,
      "so": 0
    },
    {
      "batterId": "야로고BC_이호선_9",
      "pitcherId": "물금고_김태현_11",
      "ab": 1,
      "h": 0,
      "b2": 0,
      "b3": 0,
      "hr": 0,
      "bb": 0,
      "hbp": 0,
      "so": 1
    },
    {
      "batterId": "야로고BC_이호선_9",
      "pitcherId": "물금고_김진석_49",
      "ab": 1,
      "h": 0,
      "b2": 0,
      "b3": 0,
      "hr": 0,
      "bb": 0,
      "hbp": 0,
      "so": 1
    },
    {
      "batterId": "야로고BC_이정훈_22",
      "pitcherId": "물금고_김진석_49",
      "ab": 1,
      "h": 0,
      "b2": 0,
      "b3": 0,
      "hr": 0,
      "bb": 0,
      "hbp": 0,
      "so": 0
    },
    {
      "batterId": "야로고BC_이정훈_22",
      "pitcherId": "물금고_김준영_17",
      "ab": 1,
      "h": 0,
      "b2": 0,
      "b3": 0,
      "hr": 0,
      "bb": 0,
      "hbp": 0,
      "so": 0
    }
  ]
}
