{
  "id": "38012",
  "date": "2026-05-31",
  "season": 2026,
  "home": "제주고",
  "away": "부경고",
  "score": {
    "home": 0,
    "away": 7
  },
  "batters": [
    {
      "playerId": "부경고_박재운_41",
      "name": "박재운",
      "team": "부경고",
      "ab": 4,
      "h": 1,
      "rbi": 0,
      "r": 1,
      "b2": 1,
      "b3": 0,
      "hr": 0,
      "bb": 0,
      "hbp": 0,
      "so": 1,
      "sb": 0
    },
    {
      "playerId": "부경고_김동한_0",
      "name": "김동한",
      "team": "부경고",
      "ab": 4,
      "h": 3,
      "rbi": 1,
      "r": 1,
      "b2": 2,
      "b3": 0,
      "hr": 0,
      "bb": 0,
      "hbp": 0,
      "so": 0,
      "sb": 0
    },
    {
      "playerId": "부경고_이재영_33",
      "name": "이재영",
      "team": "부경고",
      "ab": 3,
      "h": 1,
      "rbi": 0,
      "r": 0,
      "b2": 0,
      "b3": 0,
      "hr": 0,
      "bb": 0,
      "hbp": 1,
      "so": 0,
      "sb": 0
    },
    {
      "playerId": "부경고_최창빈_15",
      "name": "최창빈",
      "team": "부경고",
      "ab": 4,
      "h": 2,
      "rbi": 0,
      "r": 0,
      "b2": 0,
      "b3": 0,
      "hr": 0,
      "bb": 0,
      "hbp": 0,
      "so": 0,
      "sb": 0
    },
    {
      "playerId": "부경고_김달우_25",
      "name": "김달우",
      "team": "부경고",
      "ab": 4,
      "h": 2,
      "rbi": 0,
      "r": 2,
      "b2": 2,
      "b3": 0,
      "hr": 0,
      "bb": 0,
      "hbp": 0,
      "so": 0,
      "sb": 0
    },
    {
      "playerId": "부경고_현승준_6",
      "name": "현승준",
      "team": "부경고",
      "ab": 4,
      "h": 1,
      "rbi": 1,
      "r": 1,
      "b2": 0,
      "b3": 0,
      "hr": 0,
      "bb": 0,
      "hbp": 0,
      "so": 1,
      "sb": 0
    },
    {
      "playerId": "부경고_권세윤_2",
      "name": "권세윤",
      "team": "부경고",
      "ab": 4,
      "h": 1,
      "rbi": 1,
      "r": 0,
      "b2": 0,
      "b3": 0,
      "hr": 0,
      "bb": 0,
      "hbp": 0,
      "so": 0,
      "sb": 0
    },
    {
      "playerId": "부경고_김지호_8",
      "name": "김지호",
      "team": "부경고",
      "ab": 2,
      "h": 0,
      "rbi": 0,
      "r": 1,
      "b2": 0,
      "b3": 0,
      "hr": 0,
      "bb": 1,
      "hbp": 0,
      "so": 0,
      "sb": 0
    },
    {
      "playerId": "부경고_정승민_34",
      "name": "정승민",
      "team": "부경고",
      "ab": 3,
      "h": 1,
      "rbi": 3,
      "r": 1,
      "b2": 0,
      "b3": 0,
      "hr": 1,
      "bb": 0,
      "hbp": 0,
      "so": 2,
      "sb": 0
    },
    {
      "playerId": "제주고_주홍찬_17",
      "name": "주홍찬",
      "team": "제주고",
      "ab": 3,
      "h": 0,
      "rbi": 0,
      "r": 0,
      "b2": 0,
      "b3": 0,
      "hr": 0,
      "bb": 0,
      "hbp": 0,
      "so": 0,
      "sb": 0
    },
    {
      "playerId": "제주고_송민혁_7",
      "name": "송민혁",
      "team": "제주고",
      "ab": 2,
      "h": 0,
      "rbi": 0,
      "r": 0,
      "b2": 0,
      "b3": 0,
      "hr": 0,
      "bb": 1,
      "hbp": 0,
      "so": 2,
      "sb": 0
    },
    {
      "playerId": "제주고_윤열음_23",
      "name": "윤열음",
      "team": "제주고",
      "ab": 3,
      "h": 0,
      "rbi": 0,
      "r": 0,
      "b2": 0,
      "b3": 0,
      "hr": 0,
      "bb": 0,
      "hbp": 0,
      "so": 1,
      "sb": 0
    },
    {
      "playerId": "제주고_김서현_18",
      "name": "김서현",
      "team": "제주고",
      "ab": 3,
      "h": 1,
      "rbi": 0,
      "r": 0,
      "b2": 0,
      "b3": 0,
      "hr": 0,
      "bb": 0,
      "hbp": 0,
      "so": 1,
      "sb": 0
    },
    {
      "playerId": "제주고_신승윤_10",
      "name": "신승윤",
      "team": "제주고",
      "ab": 3,
      "h": 0,
      "rbi": 0,
      "r": 0,
      "b2": 0,
      "b3": 0,
      "hr": 0,
      "bb": 0,
      "hbp": 0,
      "so": 2,
      "sb": 0
    },
    {
      "playerId": "제주고_정수호_27",
      "name": "정수호",
      "team": "제주고",
      "ab": 1,
      "h": 0,
      "rbi": 0,
      "r": 0,
      "b2": 0,
      "b3": 0,
      "hr": 0,
      "bb": 1,
      "hbp": 1,
      "so": 0,
      "sb": 0
    },
    {
      "playerId": "제주고_석지민_1",
      "name": "석지민",
      "team": "제주고",
      "ab": 2,
      "h": 0,
      "rbi": 0,
      "r": 0,
      "b2": 0,
      "b3": 0,
      "hr": 0,
      "bb": 0,
      "hbp": 0,
      "so": 0,
      "sb": 0
    },
    {
      "playerId": "제주고_김도현_2",
      "name": "김도현",
      "team": "제주고",
      "ab": 1,
      "h": 0,
      "rbi": 0,
      "r": 0,
      "b2": 0,
      "b3": 0,
      "hr": 0,
      "bb": 0,
      "hbp": 0,
      "so": 1,
      "sb": 0
    },
    {
      "playerId": "제주고_김준범_8",
      "name": "김준범",
      "team": "제주고",
      "ab": 1,
      "h": 0,
      "rbi": 0,
      "r": 0,
      "b2": 0,
      "b3": 0,
      "hr": 0,
      "bb": 0,
      "hbp": 1,
      "so": 0,
      "sb": 0
    },
    {
      "playerId": "제주고_정지민_16",
      "name": "정지민",
      "team": "제주고",
      "ab": 1,
      "h": 0,
      "rbi": 0,
      "r": 0,
      "b2": 0,
      "b3": 0,
      "hr": 0,
      "bb": 0,
      "hbp": 0,
      "so": 1,
      "sb": 0
    },
    {
      "playerId": "제주고_이우준_5",
      "name": "이우준",
      "team": "제주고",
      "ab": 1,
      "h": 0,
      "rbi": 0,
      "r": 0,
      "b2": 0,
      "b3": 0,
      "hr": 0,
      "bb": 0,
      "hbp": 0,
      "so": 0,
      "sb": 0
    },
    {
      "playerId": "제주고_조이안_13",
      "name": "조이안",
      "team": "제주고",
      "ab": 1,
      "h": 0,
      "rbi": 0,
      "r": 0,
      "b2": 0,
      "b3": 0,
      "hr": 0,
      "bb": 0,
      "hbp": 0,
      "so": 1,
      "sb": 0
    }
  ],
  "pitchers": [
    {
      "playerId": "부경고_차효준_26",
      "name": "차효준",
      "team": "부경고",
      "outs": 15,
      "h": 0,
      "r": 0,
      "er": 0,
      "bb": 3,
      "so": 5,
      "w": 1,
      "l": 0,
      "sv": 0
    },
    {
      "playerId": "부경고_서민혁_1",
      "name": "서민혁",
      "team": "부경고",
      "outs": 6,
      "h": 1,
      "r": 0,
      "er": 0,
      "bb": 1,
      "so": 4,
      "w": 0,
      "l": 0,
      "sv": 0
    },
    {
      "playerId": "제주고_김대승_14",
      "name": "김대승",
      "team": "제주고",
      "outs": 15,
      "h": 8,
      "r": 3,
      "er": 2,
      "bb": 0,
      "so": 4,
      "w": 0,
      "l": 1,
      "sv": 0
    },
    {
      "playerId": "제주고_이지훈_29",
      "name": "이지훈",
      "team": "제주고",
      "outs": 2,
      "h": 4,
      "r": 4,
      "er": 4,
      "bb": 2,
      "so": 0,
      "w": 0,
      "l": 0,
      "sv": 0
    },
    {
      "playerId": "제주고_최혜성_22",
      "name": "최혜성",
      "team": "제주고",
      "outs": 4,
      "h": 0,
      "r": 0,
      "er": 0,
      "bb": 0,
      "so": 0,
      "w": 0,
      "l": 0,
      "sv": 0
    }
  ],
  "matchups": [
    {
      "batterId": "부경고_박재운_41",
      "pitcherId": "제주고_김대승_14",
      "ab": 3,
      "h": 1,
      "b2": 1,
      "b3": 0,
      "hr": 0,
      "bb": 0,
      "hbp": 0,
      "so": 1
    },
    {
      "batterId": "부경고_박재운_41",
      "pitcherId": "제주고_이지훈_29",
      "ab": 1,
      "h": 0,
      "b2": 0,
      "b3": 0,
      "hr": 0,
      "bb": 0,
      "hbp": 0,
      "so": 0
    },
    {
      "batterId": "부경고_김동한_0",
      "pitcherId": "제주고_김대승_14",
      "ab": 3,
      "h": 2,
      "b2": 1,
      "b3": 0,
      "hr": 0,
      "bb": 0,
      "hbp": 0,
      "so": 0
    },
    {
      "batterId": "부경고_김동한_0",
      "pitcherId": "제주고_이지훈_29",
      "ab": 1,
      "h": 1,
      "b2": 1,
      "b3": 0,
      "hr": 0,
      "bb": 0,
      "hbp": 0,
      "so": 0
    },
    {
      "batterId": "부경고_이재영_33",
      "pitcherId": "제주고_김대승_14",
      "ab": 3,
      "h": 1,
      "b2": 0,
      "b3": 0,
      "hr": 0,
      "bb": 0,
      "hbp": 0,
      "so": 0
    },
    {
      "batterId": "부경고_이재영_33",
      "pitcherId": "제주고_이지훈_29",
      "ab": 0,
      "h": 0,
      "b2": 0,
      "b3": 0,
      "hr": 0,
      "bb": 0,
      "hbp": 1,
      "so": 0
    },
    {
      "batterId": "부경고_최창빈_15",
      "pitcherId": "제주고_김대승_14",
      "ab": 3,
      "h": 2,
      "b2": 0,
      "b3": 0,
      "hr": 0,
      "bb": 0,
      "hbp": 0,
      "so": 0
    },
    {
      "batterId": "부경고_최창빈_15",
      "pitcherId": "제주고_이지훈_29",
      "ab": 1,
      "h": 0,
      "b2": 0,
      "b3": 0,
      "hr": 0,
      "bb": 0,
      "hbp": 0,
      "so": 0
    },
    {
      "batterId": "부경고_김달우_25",
      "pitcherId": "제주고_김대승_14",
      "ab": 2,
      "h": 1,
      "b2": 1,
      "b3": 0,
      "hr": 0,
      "bb": 0,
      "hbp": 0,
      "so": 0
    },
    {
      "batterId": "부경고_김달우_25",
      "pitcherId": "제주고_이지훈_29",
      "ab": 1,
      "h": 1,
      "b2": 1,
      "b3": 0,
      "hr": 0,
      "bb": 0,
      "hbp": 0,
      "so": 0
    },
    {
      "batterId": "부경고_김달우_25",
      "pitcherId": "제주고_최혜성_22",
      "ab": 1,
      "h": 0,
      "b2": 0,
      "b3": 0,
      "hr": 0,
      "bb": 0,
      "hbp": 0,
      "so": 0
    },
    {
      "batterId": "부경고_현승준_6",
      "pitcherId": "제주고_김대승_14",
      "ab": 2,
      "h": 0,
      "b2": 0,
      "b3": 0,
      "hr": 0,
      "bb": 0,
      "hbp": 0,
      "so": 1
    },
    {
      "batterId": "부경고_현승준_6",
      "pitcherId": "제주고_이지훈_29",
      "ab": 1,
      "h": 1,
      "b2": 0,
      "b3": 0,
      "hr": 0,
      "bb": 0,
      "hbp": 0,
      "so": 0
    },
    {
      "batterId": "부경고_현승준_6",
      "pitcherId": "제주고_최혜성_22",
      "ab": 1,
      "h": 0,
      "b2": 0,
      "b3": 0,
      "hr": 0,
      "bb": 0,
      "hbp": 0,
      "so": 0
    },
    {
      "batterId": "부경고_권세윤_2",
      "pitcherId": "제주고_김대승_14",
      "ab": 2,
      "h": 1,
      "b2": 0,
      "b3": 0,
      "hr": 0,
      "bb": 0,
      "hbp": 0,
      "so": 0
    },
    {
      "batterId": "부경고_권세윤_2",
      "pitcherId": "제주고_이지훈_29",
      "ab": 1,
      "h": 0,
      "b2": 0,
      "b3": 0,
      "hr": 0,
      "bb": 0,
      "hbp": 0,
      "so": 0
    },
    {
      "batterId": "부경고_권세윤_2",
      "pitcherId": "제주고_최혜성_22",
      "ab": 1,
      "h": 0,
      "b2": 0,
      "b3": 0,
      "hr": 0,
      "bb": 0,
      "hbp": 0,
      "so": 0
    },
    {
      "batterId": "부경고_김지호_8",
      "pitcherId": "제주고_김대승_14",
      "ab": 2,
      "h": 0,
      "b2": 0,
      "b3": 0,
      "hr": 0,
      "bb": 0,
      "hbp": 0,
      "so": 0
    },
    {
      "batterId": "부경고_김지호_8",
      "pitcherId": "제주고_이지훈_29",
      "ab": 0,
      "h": 0,
      "b2": 0,
      "b3": 0,
      "hr": 0,
      "bb": 1,
      "hbp": 0,
      "so": 0
    },
    {
      "batterId": "부경고_정승민_34",
      "pitcherId": "제주고_김대승_14",
      "ab": 2,
      "h": 0,
      "b2": 0,
      "b3": 0,
      "hr": 0,
      "bb": 0,
      "hbp": 0,
      "so": 2
    },
    {
      "batterId": "부경고_정승민_34",
      "pitcherId": "제주고_이지훈_29",
      "ab": 1,
      "h": 1,
      "b2": 0,
      "b3": 0,
      "hr": 1,
      "bb": 0,
      "hbp": 0,
      "so": 0
    },
    {
      "batterId": "제주고_주홍찬_17",
      "pitcherId": "부경고_차효준_26",
      "ab": 3,
      "h": 0,
      "b2": 0,
      "b3": 0,
      "hr": 0,
      "bb": 0,
      "hbp": 0,
      "so": 0
    },
    {
      "batterId": "제주고_송민혁_7",
      "pitcherId": "부경고_차효준_26",
      "ab": 2,
      "h": 0,
      "b2": 0,
      "b3": 0,
      "hr": 0,
      "bb": 0,
      "hbp": 0,
      "so": 2
    },
    {
      "batterId": "제주고_송민혁_7",
      "pitcherId": "부경고_서민혁_1",
      "ab": 0,
      "h": 0,
      "b2": 0,
      "b3": 0,
      "hr": 0,
      "bb": 1,
      "hbp": 0,
      "so": 0
    },
    {
      "batterId": "제주고_윤열음_23",
      "pitcherId": "부경고_차효준_26",
      "ab": 2,
      "h": 0,
      "b2": 0,
      "b3": 0,
      "hr": 0,
      "bb": 0,
      "hbp": 0,
      "so": 1
    },
    {
      "batterId": "제주고_윤열음_23",
      "pitcherId": "부경고_서민혁_1",
      "ab": 1,
      "h": 0,
      "b2": 0,
      "b3": 0,
      "hr": 0,
      "bb": 0,
      "hbp": 0,
      "so": 0
    },
    {
      "batterId": "제주고_김서현_18",
      "pitcherId": "부경고_차효준_26",
      "ab": 2,
      "h": 0,
      "b2": 0,
      "b3": 0,
      "hr": 0,
      "bb": 0,
      "hbp": 0,
      "so": 1
    },
    {
      "batterId": "제주고_김서현_18",
      "pitcherId": "부경고_서민혁_1",
      "ab": 1,
      "h": 1,
      "b2": 0,
      "b3": 0,
      "hr": 0,
      "bb": 0,
      "hbp": 0,
      "so": 0
    },
    {
      "batterId": "제주고_신승윤_10",
      "pitcherId": "부경고_차효준_26",
      "ab": 2,
      "h": 0,
      "b2": 0,
      "b3": 0,
      "hr": 0,
      "bb": 0,
      "hbp": 0,
      "so": 1
    },
    {
      "batterId": "제주고_신승윤_10",
      "pitcherId": "부경고_서민혁_1",
      "ab": 1,
      "h": 0,
      "b2": 0,
      "b3": 0,
      "hr": 0,
      "bb": 0,
      "hbp": 0,
      "so": 1
    },
    {
      "batterId": "제주고_정수호_27",
      "pitcherId": "부경고_차효준_26",
      "ab": 0,
      "h": 0,
      "b2": 0,
      "b3": 0,
      "hr": 0,
      "bb": 1,
      "hbp": 1,
      "so": 0
    },
    {
      "batterId": "제주고_정수호_27",
      "pitcherId": "부경고_서민혁_1",
      "ab": 1,
      "h": 0,
      "b2": 0,
      "b3": 0,
      "hr": 0,
      "bb": 0,
      "hbp": 0,
      "so": 0
    },
    {
      "batterId": "제주고_석지민_1",
      "pitcherId": "부경고_차효준_26",
      "ab": 2,
      "h": 0,
      "b2": 0,
      "b3": 0,
      "hr": 0,
      "bb": 0,
      "hbp": 0,
      "so": 0
    },
    {
      "batterId": "제주고_김도현_2",
      "pitcherId": "부경고_서민혁_1",
      "ab": 1,
      "h": 0,
      "b2": 0,
      "b3": 0,
      "hr": 0,
      "bb": 0,
      "hbp": 0,
      "so": 1
    },
    {
      "batterId": "제주고_김준범_8",
      "pitcherId": "부경고_차효준_26",
      "ab": 1,
      "h": 0,
      "b2": 0,
      "b3": 0,
      "hr": 0,
      "bb": 0,
      "hbp": 1,
      "so": 0
    },
    {
      "batterId": "제주고_정지민_16",
      "pitcherId": "부경고_서민혁_1",
      "ab": 1,
      "h": 0,
      "b2": 0,
      "b3": 0,
      "hr": 0,
      "bb": 0,
      "hbp": 0,
      "so": 1
    },
    {
      "batterId": "제주고_이우준_5",
      "pitcherId": "부경고_차효준_26",
      "ab": 2,
      "h": 0,
      "b2": 0,
      "b3": 0,
      "hr": 0,
      "bb": 0,
      "hbp": 0,
      "so": 0
    },
    {
      "batterId": "제주고_조이안_13",
      "pitcherId": "부경고_서민혁_1",
      "ab": 1,
      "h": 0,
      "b2": 0,
      "b3": 0,
      "hr": 0,
      "bb": 0,
      "hbp": 0,
      "so": 1
    }
  ],
  "title": "2026 고교야구 주말리그 후반기(경상권C)"
}
