{"id":"제주고_박창민_18","name":"박창민","team":"제주고","position":"투수","season":2025,"gameLog":[{"gameId":"35066","date":"2025-05-31","team":"제주고","opponent":"대구상원","line":"1.2이닝 3자책 0탈삼진","title":"2025 고교야구 주말리그 후반기 (경상권B)","pStat":{"outs":5,"h":1,"r":4,"er":3,"bb":5,"so":0,"w":0,"l":0,"sv":0}},{"gameId":"34866","date":"2025-05-25","team":"제주고","opponent":"대구고","line":"1이닝 3자책 0탈삼진","title":"2025 고교야구 주말리그 후반기 (경상권B)","pStat":{"outs":3,"h":1,"r":3,"er":3,"bb":6,"so":0,"w":0,"l":0,"sv":0}},{"gameId":"34864","date":"2025-05-24","team":"제주고","opponent":"대구북구","line":"1.2이닝 1자책 3탈삼진","title":"2025 고교야구 주말리그 후반기 (경상권B)","pStat":{"outs":5,"h":3,"r":1,"er":1,"bb":1,"so":3,"w":0,"l":0,"sv":0}},{"gameId":"34102","date":"2025-04-26","team":"제주고","opponent":"경북고","line":"1이닝 3자책 2탈삼진","title":"2025 고교야구 주말리그 전반기 (경상권B)","pStat":{"outs":3,"h":3,"r":3,"er":3,"bb":5,"so":2,"w":0,"l":0,"sv":0}},{"gameId":"33925","date":"2025-04-19","team":"제주고","opponent":"대구상원고","line":"2이닝 0자책 3탈삼진","title":"2025 고교야구 주말리그 전반기 (경상권B)","pStat":{"outs":6,"h":2,"r":0,"er":0,"bb":0,"so":3,"w":0,"l":0,"sv":0}},{"gameId":"34407","date":"2025-03-29","team":"제주고","opponent":"상동고","line":"1이닝 1자책 1탈삼진","title":"2025 신세계 이마트배 전국고교야구대회","pStat":{"outs":3,"h":3,"r":3,"er":1,"bb":1,"so":1,"w":0,"l":0,"sv":0}},{"gameId":"34407","date":"2025-03-29","team":"제주고","opponent":"상동고","line":"0타수 0안타","title":"2025 신세계 이마트배 전국고교야구대회","bStat":{"ab":0,"h":0,"b2":0,"b3":0,"hr":0,"rbi":0,"r":0,"bb":0,"hbp":0,"so":0,"sb":0}},{"gameId":"34100","date":"2025-03-22","team":"제주고","opponent":"대구고","line":"1.1이닝 3자책 0탈삼진 패","title":"2025 고교야구 주말리그 전반기 (경상권B)","pStat":{"outs":4,"h":2,"r":3,"er":3,"bb":4,"so":0,"w":0,"l":1,"sv":0}},{"gameId":"34100","date":"2025-03-22","team":"제주고","opponent":"대구고","line":"0타수 0안타","title":"2025 고교야구 주말리그 전반기 (경상권B)","bStat":{"ab":0,"h":0,"b2":0,"b3":0,"hr":0,"rbi":0,"r":0,"bb":0,"hbp":0,"so":0,"sb":0}},{"gameId":"34098","date":"2025-03-16","team":"제주고","opponent":"대구북구","line":"2이닝 1자책 1탈삼진","title":"2025 고교야구 주말리그 전반기 (경상권B)","pStat":{"outs":6,"h":4,"r":6,"er":1,"bb":3,"so":1,"w":0,"l":0,"sv":0}},{"gameId":"33916","date":"2025-03-09","team":"제주고","opponent":"경북고","line":"0.1이닝 0자책 0탈삼진","title":"2025 고교야구 주말리그 전반기 (경상권B)","pStat":{"outs":1,"h":0,"r":0,"er":0,"bb":0,"so":0,"w":0,"l":0,"sv":0}},{"gameId":"33916","date":"2025-03-09","team":"제주고","opponent":"경북고","line":"0타수 0안타","title":"2025 고교야구 주말리그 전반기 (경상권B)","bStat":{"ab":0,"h":0,"b2":0,"b3":0,"hr":0,"rbi":0,"r":0,"bb":0,"hbp":0,"so":0,"sb":0}},{"gameId":"33914","date":"2025-03-08","team":"제주고","opponent":"대구상원","line":"1이닝 7자책 2탈삼진","title":"2025 고교야구 주말리그 전반기 (경상권B)","pStat":{"outs":3,"h":3,"r":7,"er":7,"bb":5,"so":2,"w":0,"l":0,"sv":0}}],"number":"18","bats":"우","throws":"우","grade":"3","personNo":"201702003015","region":"제주","batting":{"g":3,"pa":0,"ab":0,"r":0,"h":0,"b2":0,"b3":0,"hr":0,"rbi":0,"bb":0,"hbp":0,"so":0,"sb":0,"sh":0,"sf":0,"ibb":0,"e":1,"avg":0,"obp":0,"slg":0},"pitching":{"g":10,"w":0,"l":1,"sv":0,"ip":13,"h":22,"hr":0,"r":30,"er":22,"bb":30,"so":12,"bf":90,"np":343,"era":15.23,"whip":4},"matchups":[{"batterId":"상동고_고규민_25","batterName":"고규민","pitcherId":"제주고_박창민_18","pitcherName":"박창민","pa":1,"ab":1,"h":1,"b2":0,"b3":0,"hr":0,"bb":0,"hbp":0,"so":0,"avg":1},{"batterId":"대구상원고_고재욱_13","batterName":"고재욱","pitcherId":"제주고_박창민_18","pitcherName":"박창민","pa":3,"ab":2,"h":1,"b2":0,"b3":0,"hr":0,"bb":0,"hbp":1,"so":0,"avg":0.5},{"batterId":"대구북구SC(U-18)_권성민_0","batterName":"권성민","pitcherId":"제주고_박창민_18","pitcherName":"박창민","pa":1,"ab":1,"h":0,"b2":0,"b3":0,"hr":0,"bb":0,"hbp":0,"so":1,"avg":0},{"batterId":"대구상원고_권준재_22","batterName":"권준재","pitcherId":"제주고_박창민_18","pitcherName":"박창민","pa":1,"ab":1,"h":1,"b2":1,"b3":0,"hr":0,"bb":0,"hbp":0,"so":0,"avg":1},{"batterId":"경북고_권현규_6","batterName":"권현규","pitcherId":"제주고_박창민_18","pitcherName":"박창민","pa":1,"ab":1,"h":0,"b2":0,"b3":0,"hr":0,"bb":0,"hbp":0,"so":0,"avg":0},{"batterId":"대구고_기현_51","batterName":"기현","pitcherId":"제주고_박창민_18","pitcherName":"박창민","pa":2,"ab":2,"h":2,"b2":0,"b3":0,"hr":0,"bb":0,"hbp":0,"so":0,"avg":1},{"batterId":"대구고_김대욱_0","batterName":"김대욱","pitcherId":"제주고_박창민_18","pitcherName":"박창민","pa":1,"ab":0,"h":0,"b2":0,"b3":0,"hr":0,"bb":1,"hbp":0,"so":0,"avg":0},{"batterId":"상동고_김도현_53","batterName":"김도현","pitcherId":"제주고_박창민_18","pitcherName":"박창민","pa":2,"ab":2,"h":0,"b2":0,"b3":0,"hr":0,"bb":0,"hbp":0,"so":0,"avg":0},{"batterId":"대구상원고_김동연_14","batterName":"김동연","pitcherId":"제주고_박창민_18","pitcherName":"박창민","pa":1,"ab":1,"h":0,"b2":0,"b3":0,"hr":0,"bb":0,"hbp":0,"so":1,"avg":0},{"batterId":"대구북구SC(U-18)_김두현_6","batterName":"김두현","pitcherId":"제주고_박창민_18","pitcherName":"박창민","pa":2,"ab":1,"h":1,"b2":0,"b3":0,"hr":0,"bb":0,"hbp":1,"so":0,"avg":1},{"batterId":"대구상원고_김명규_20","batterName":"김명규","pitcherId":"제주고_박창민_18","pitcherName":"박창민","pa":2,"ab":2,"h":1,"b2":0,"b3":0,"hr":0,"bb":0,"hbp":0,"so":0,"avg":0.5},{"batterId":"상동고_김민서_3","batterName":"김민서","pitcherId":"제주고_박창민_18","pitcherName":"박창민","pa":1,"ab":1,"h":0,"b2":0,"b3":0,"hr":0,"bb":0,"hbp":0,"so":0,"avg":0},{"batterId":"상동고_김민성_10","batterName":"김민성","pitcherId":"제주고_박창민_18","pitcherName":"박창민","pa":1,"ab":1,"h":0,"b2":0,"b3":0,"hr":0,"bb":0,"hbp":0,"so":0,"avg":0},{"batterId":"대구상원고_김민재_21","batterName":"김민재","pitcherId":"제주고_박창민_18","pitcherName":"박창민","pa":3,"ab":2,"h":1,"b2":0,"b3":0,"hr":0,"bb":0,"hbp":1,"so":0,"avg":0.5},{"batterId":"경북고_김민제_50","batterName":"김민제","pitcherId":"제주고_박창민_18","pitcherName":"박창민","pa":1,"ab":0,"h":0,"b2":0,"b3":0,"hr":0,"bb":1,"hbp":0,"so":0,"avg":0},{"batterId":"대구북구SC(U-18)_김민준_5","batterName":"김민준","pitcherId":"제주고_박창민_18","pitcherName":"박창민","pa":2,"ab":2,"h":2,"b2":0,"b3":1,"hr":0,"bb":0,"hbp":0,"so":0,"avg":1},{"batterId":"대구상원고_김상하_31","batterName":"김상하","pitcherId":"제주고_박창민_18","pitcherName":"박창민","pa":1,"ab":1,"h":0,"b2":0,"b3":0,"hr":0,"bb":0,"hbp":0,"so":0,"avg":0},{"batterId":"대구상원고_김성휘_10","batterName":"김성휘","pitcherId":"제주고_박창민_18","pitcherName":"박창민","pa":1,"ab":1,"h":1,"b2":0,"b3":0,"hr":0,"bb":0,"hbp":0,"so":0,"avg":1},{"batterId":"대구북구SC(U-18)_김예찬_10","batterName":"김예찬","pitcherId":"제주고_박창민_18","pitcherName":"박창민","pa":2,"ab":2,"h":1,"b2":0,"b3":1,"hr":0,"bb":0,"hbp":0,"so":0,"avg":0.5},{"batterId":"상동고_김우진_12","batterName":"김우진","pitcherId":"제주고_박창민_18","pitcherName":"박창민","pa":1,"ab":1,"h":0,"b2":0,"b3":0,"hr":0,"bb":0,"hbp":0,"so":0,"avg":0},{"batterId":"대구북구SC(U-18)_김정훈_2","batterName":"김정훈","pitcherId":"제주고_박창민_18","pitcherName":"박창민","pa":2,"ab":1,"h":0,"b2":0,"b3":0,"hr":0,"bb":1,"hbp":0,"so":0,"avg":0},{"batterId":"대구고_김주원_47","batterName":"김주원","pitcherId":"제주고_박창민_18","pitcherName":"박창민","pa":1,"ab":0,"h":0,"b2":0,"b3":0,"hr":0,"bb":0,"hbp":1,"so":0,"avg":0},{"batterId":"경북고_김주한_5","batterName":"김주한","pitcherId":"제주고_박창민_18","pitcherName":"박창민","pa":1,"ab":1,"h":0,"b2":0,"b3":0,"hr":0,"bb":0,"hbp":0,"so":1,"avg":0},{"batterId":"대구고_김창범_16","batterName":"김창범","pitcherId":"제주고_박창민_18","pitcherName":"박창민","pa":3,"ab":1,"h":0,"b2":0,"b3":0,"hr":0,"bb":2,"hbp":0,"so":0,"avg":0},{"batterId":"대구북구SC(U-18)_남우영_15","batterName":"남우영","pitcherId":"제주고_박창민_18","pitcherName":"박창민","pa":1,"ab":1,"h":0,"b2":0,"b3":0,"hr":0,"bb":0,"hbp":0,"so":1,"avg":0},{"batterId":"대구상원고_남태웅_7","batterName":"남태웅","pitcherId":"제주고_박창민_18","pitcherName":"박창민","pa":2,"ab":1,"h":0,"b2":0,"b3":0,"hr":0,"bb":0,"hbp":1,"so":0,"avg":0},{"batterId":"대구고_두동현_24","batterName":"두동현","pitcherId":"제주고_박창민_18","pitcherName":"박창민","pa":2,"ab":1,"h":1,"b2":0,"b3":0,"hr":0,"bb":1,"hbp":0,"so":0,"avg":1},{"batterId":"대구상원고_문경원_1","batterName":"문경원","pitcherId":"제주고_박창민_18","pitcherName":"박창민","pa":3,"ab":2,"h":0,"b2":0,"b3":0,"hr":0,"bb":1,"hbp":0,"so":0,"avg":0},{"batterId":"대구고_민상훈_33","batterName":"민상훈","pitcherId":"제주고_박창민_18","pitcherName":"박창민","pa":2,"ab":1,"h":0,"b2":0,"b3":0,"hr":0,"bb":0,"hbp":1,"so":0,"avg":0},{"batterId":"대구고_박승찬_7","batterName":"박승찬","pitcherId":"제주고_박창민_18","pitcherName":"박창민","pa":2,"ab":1,"h":0,"b2":0,"b3":0,"hr":0,"bb":1,"hbp":0,"so":0,"avg":0},{"batterId":"제주고_박창민_18","batterName":"박창민","pitcherId":"상동고_김민성_10","pitcherName":"김민성","pa":1,"ab":1,"h":0,"b2":0,"b3":0,"hr":0,"bb":0,"hbp":0,"so":0,"avg":0},{"batterId":"대구고_배다승_52","batterName":"배다승","pitcherId":"제주고_박창민_18","pitcherName":"박창민","pa":3,"ab":2,"h":1,"b2":0,"b3":0,"hr":1,"bb":0,"hbp":1,"so":0,"avg":0.5},{"batterId":"대구상원고_서승환_27","batterName":"서승환","pitcherId":"제주고_박창민_18","pitcherName":"박창민","pa":3,"ab":1,"h":0,"b2":0,"b3":0,"hr":0,"bb":2,"hbp":0,"so":1,"avg":0},{"batterId":"상동고_선한빛_13","batterName":"선한빛","pitcherId":"제주고_박창민_18","pitcherName":"박창민","pa":1,"ab":1,"h":1,"b2":1,"b3":0,"hr":0,"bb":0,"hbp":0,"so":0,"avg":1},{"batterId":"대구북구SC(U-18)_손정기_22","batterName":"손정기","pitcherId":"제주고_박창민_18","pitcherName":"박창민","pa":2,"ab":2,"h":0,"b2":0,"b3":0,"hr":0,"bb":0,"hbp":0,"so":0,"avg":0},{"batterId":"상동고_신명규_7","batterName":"신명규","pitcherId":"제주고_박창민_18","pitcherName":"박창민","pa":1,"ab":0,"h":0,"b2":0,"b3":0,"hr":0,"bb":1,"hbp":0,"so":0,"avg":0},{"batterId":"대구상원고_신원우_53","batterName":"신원우","pitcherId":"제주고_박창민_18","pitcherName":"박창민","pa":3,"ab":2,"h":0,"b2":0,"b3":0,"hr":0,"bb":0,"hbp":1,"so":1,"avg":0},{"batterId":"경북고_신지후_28","batterName":"신지후","pitcherId":"제주고_박창민_18","pitcherName":"박창민","pa":1,"ab":0,"h":0,"b2":0,"b3":0,"hr":0,"bb":1,"hbp":0,"so":0,"avg":0},{"batterId":"대구상원고_엄유상_9","batterName":"엄유상","pitcherId":"제주고_박창민_18","pitcherName":"박창민","pa":3,"ab":3,"h":1,"b2":0,"b3":0,"hr":0,"bb":0,"hbp":0,"so":0,"avg":0.333},{"batterId":"대구고_오승재_3","batterName":"오승재","pitcherId":"제주고_박창민_18","pitcherName":"박창민","pa":3,"ab":1,"h":0,"b2":0,"b3":0,"hr":0,"bb":2,"hbp":0,"so":0,"avg":0},{"batterId":"대구상원고_유승민_19","batterName":"유승민","pitcherId":"제주고_박창민_18","pitcherName":"박창민","pa":2,"ab":1,"h":0,"b2":0,"b3":0,"hr":0,"bb":1,"hbp":0,"so":0,"avg":0},{"batterId":"상동고_윤도규_20","batterName":"윤도규","pitcherId":"제주고_박창민_18","pitcherName":"박창민","pa":1,"ab":1,"h":0,"b2":0,"b3":0,"hr":0,"bb":0,"hbp":0,"so":0,"avg":0},{"batterId":"경북고_이동호_7","batterName":"이동호","pitcherId":"제주고_박창민_18","pitcherName":"박창민","pa":1,"ab":1,"h":1,"b2":0,"b3":0,"hr":0,"bb":0,"hbp":0,"so":0,"avg":1},{"batterId":"경북고_이성찬_9","batterName":"이성찬","pitcherId":"제주고_박창민_18","pitcherName":"박창민","pa":1,"ab":0,"h":0,"b2":0,"b3":0,"hr":0,"bb":0,"hbp":1,"so":0,"avg":0},{"batterId":"대구북구SC(U-18)_이시우_3","batterName":"이시우","pitcherId":"제주고_박창민_18","pitcherName":"박창민","pa":3,"ab":2,"h":0,"b2":0,"b3":0,"hr":0,"bb":1,"hbp":0,"so":1,"avg":0},{"batterId":"대구고_이재준_27","batterName":"이재준","pitcherId":"제주고_박창민_18","pitcherName":"박창민","pa":2,"ab":0,"h":0,"b2":0,"b3":0,"hr":0,"bb":2,"hbp":0,"so":0,"avg":0},{"batterId":"대구고_이지백_15","batterName":"이지백","pitcherId":"제주고_박창민_18","pitcherName":"박창민","pa":1,"ab":0,"h":0,"b2":0,"b3":0,"hr":0,"bb":1,"hbp":0,"so":0,"avg":0},{"batterId":"상동고_이태환_34","batterName":"이태환","pitcherId":"제주고_박창민_18","pitcherName":"박창민","pa":1,"ab":1,"h":1,"b2":0,"b3":0,"hr":0,"bb":0,"hbp":0,"so":0,"avg":1},{"batterId":"경북고_이한진_12","batterName":"이한진","pitcherId":"제주고_박창민_18","pitcherName":"박창민","pa":1,"ab":1,"h":0,"b2":0,"b3":0,"hr":0,"bb":0,"hbp":0,"so":1,"avg":0},{"batterId":"상동고_이현용_8","batterName":"이현용","pitcherId":"제주고_박창민_18","pitcherName":"박창민","pa":1,"ab":1,"h":0,"b2":0,"b3":0,"hr":0,"bb":0,"hbp":0,"so":0,"avg":0},{"batterId":"대구북구SC(U-18)_이현준_8","batterName":"이현준","pitcherId":"제주고_박창민_18","pitcherName":"박창민","pa":3,"ab":2,"h":2,"b2":0,"b3":0,"hr":0,"bb":1,"hbp":0,"so":0,"avg":1},{"batterId":"대구상원고_정구현_6","batterName":"정구현","pitcherId":"제주고_박창민_18","pitcherName":"박창민","pa":3,"ab":1,"h":0,"b2":0,"b3":0,"hr":0,"bb":2,"hbp":0,"so":0,"avg":0},{"batterId":"상동고_정민성_50","batterName":"정민성","pitcherId":"제주고_박창민_18","pitcherName":"박창민","pa":1,"ab":1,"h":0,"b2":0,"b3":0,"hr":0,"bb":0,"hbp":0,"so":0,"avg":0},{"batterId":"대구상원고_조민수_59","batterName":"조민수","pitcherId":"제주고_박창민_18","pitcherName":"박창민","pa":1,"ab":1,"h":0,"b2":0,"b3":0,"hr":0,"bb":0,"hbp":0,"so":0,"avg":0},{"batterId":"경북고_최우준_15","batterName":"최우준","pitcherId":"제주고_박창민_18","pitcherName":"박창민","pa":1,"ab":0,"h":0,"b2":0,"b3":0,"hr":0,"bb":1,"hbp":0,"so":0,"avg":0},{"batterId":"상동고_최윤우_52","batterName":"최윤우","pitcherId":"제주고_박창민_18","pitcherName":"박창민","pa":1,"ab":1,"h":0,"b2":0,"b3":0,"hr":0,"bb":0,"hbp":0,"so":1,"avg":0},{"batterId":"대구상원고_피창현_3","batterName":"피창현","pitcherId":"제주고_박창민_18","pitcherName":"박창민","pa":3,"ab":2,"h":1,"b2":0,"b3":0,"hr":0,"bb":0,"hbp":1,"so":1,"avg":0.5}]}