[{"batterId":"개성고_강영은_7","batterName":"강영은","pitcherId":"제주고_정수호_27","pitcherName":"정수호","pa":1,"ab":1,"h":0,"b2":0,"b3":0,"hr":0,"bb":0,"hbp":0,"so":0,"avg":0},{"batterId":"개성고_김현수_27","batterName":"김현수","pitcherId":"제주고_정수호_27","pitcherName":"정수호","pa":1,"ab":0,"h":0,"b2":0,"b3":0,"hr":0,"bb":1,"hbp":0,"so":0,"avg":0},{"batterId":"개성고_이도경_17","batterName":"이도경","pitcherId":"제주고_정수호_27","pitcherName":"정수호","pa":1,"ab":1,"h":0,"b2":0,"b3":0,"hr":0,"bb":0,"hbp":0,"so":0,"avg":0},{"batterId":"개성고_이상원_39","batterName":"이상원","pitcherId":"제주고_정수호_27","pitcherName":"정수호","pa":1,"ab":1,"h":1,"b2":0,"b3":0,"hr":0,"bb":0,"hbp":0,"so":0,"avg":1},{"batterId":"개성고_이승범_1","batterName":"이승범","pitcherId":"제주고_정수호_27","pitcherName":"정수호","pa":1,"ab":1,"h":1,"b2":0,"b3":0,"hr":0,"bb":0,"hbp":0,"so":0,"avg":1},{"batterId":"개성고_전건우_5","batterName":"전건우","pitcherId":"제주고_정수호_27","pitcherName":"정수호","pa":1,"ab":1,"h":0,"b2":0,"b3":0,"hr":0,"bb":0,"hbp":0,"so":0,"avg":0},{"batterId":"제주고_정수호_27","batterName":"정수호","pitcherId":"부산고_고민석_52","pitcherName":"고민석","pa":1,"ab":1,"h":0,"b2":0,"b3":0,"hr":0,"bb":0,"hbp":0,"so":0,"avg":0},{"batterId":"제주고_정수호_27","batterName":"정수호","pitcherId":"부산공업고_곽도현_17","pitcherName":"곽도현","pa":2,"ab":2,"h":1,"b2":1,"b3":0,"hr":0,"bb":0,"hbp":0,"so":1,"avg":0.5},{"batterId":"제주고_정수호_27","batterName":"정수호","pitcherId":"서울자동차고_곽동엽_7","pitcherName":"곽동엽","pa":2,"ab":2,"h":0,"b2":0,"b3":0,"hr":0,"bb":0,"hbp":0,"so":2,"avg":0},{"batterId":"제주고_정수호_27","batterName":"정수호","pitcherId":"경남고_권영인_18","pitcherName":"권영인","pa":1,"ab":0,"h":0,"b2":0,"b3":0,"hr":0,"bb":1,"hbp":0,"so":0,"avg":0},{"batterId":"제주고_정수호_27","batterName":"정수호","pitcherId":"부산고_김도원_11","pitcherName":"김도원","pa":2,"ab":2,"h":0,"b2":0,"b3":0,"hr":0,"bb":0,"hbp":0,"so":0,"avg":0},{"batterId":"제주고_정수호_27","batterName":"정수호","pitcherId":"부산공업고_김민재_16","pitcherName":"김민재","pa":1,"ab":1,"h":0,"b2":0,"b3":0,"hr":0,"bb":0,"hbp":0,"so":0,"avg":0},{"batterId":"제주고_정수호_27","batterName":"정수호","pitcherId":"개성고_김재성_45","pitcherName":"김재성","pa":1,"ab":0,"h":0,"b2":0,"b3":0,"hr":0,"bb":1,"hbp":0,"so":0,"avg":0},{"batterId":"제주고_정수호_27","batterName":"정수호","pitcherId":"부산고_김지후_15","pitcherName":"김지후","pa":1,"ab":1,"h":0,"b2":0,"b3":0,"hr":0,"bb":0,"hbp":0,"so":1,"avg":0},{"batterId":"제주고_정수호_27","batterName":"정수호","pitcherId":"울산BC(U-18)_류경덕_1","pitcherName":"류경덕","pa":2,"ab":2,"h":0,"b2":0,"b3":0,"hr":0,"bb":0,"hbp":0,"so":0,"avg":0},{"batterId":"제주고_정수호_27","batterName":"정수호","pitcherId":"경남고_문주혁_11","pitcherName":"문주혁","pa":2,"ab":2,"h":1,"b2":0,"b3":0,"hr":0,"bb":0,"hbp":0,"so":1,"avg":0.5},{"batterId":"제주고_정수호_27","batterName":"정수호","pitcherId":"개성고_민경선_18","pitcherName":"민경선","pa":3,"ab":3,"h":0,"b2":0,"b3":0,"hr":0,"bb":0,"hbp":0,"so":2,"avg":0},{"batterId":"제주고_정수호_27","batterName":"정수호","pitcherId":"울산BC(U-18)_박동규_11","pitcherName":"박동규","pa":6,"ab":6,"h":2,"b2":0,"b3":0,"hr":0,"bb":0,"hbp":0,"so":4,"avg":0.333},{"batterId":"제주고_정수호_27","batterName":"정수호","pitcherId":"경남고_박찬휘_19","pitcherName":"박찬휘","pa":1,"ab":1,"h":0,"b2":0,"b3":0,"hr":0,"bb":0,"hbp":0,"so":0,"avg":0},{"batterId":"제주고_정수호_27","batterName":"정수호","pitcherId":"부경고_서민혁_1","pitcherName":"서민혁","pa":1,"ab":1,"h":0,"b2":0,"b3":0,"hr":0,"bb":0,"hbp":0,"so":0,"avg":0},{"batterId":"제주고_정수호_27","batterName":"정수호","pitcherId":"라온고_유강현_2","pitcherName":"유강현","pa":1,"ab":1,"h":0,"b2":0,"b3":0,"hr":0,"bb":0,"hbp":0,"so":0,"avg":0},{"batterId":"제주고_정수호_27","batterName":"정수호","pitcherId":"라온고_유수혁_18","pitcherName":"유수혁","pa":1,"ab":1,"h":0,"b2":0,"b3":0,"hr":0,"bb":0,"hbp":0,"so":1,"avg":0},{"batterId":"제주고_정수호_27","batterName":"정수호","pitcherId":"개성고_이대규_41","pitcherName":"이대규","pa":1,"ab":1,"h":1,"b2":0,"b3":0,"hr":0,"bb":0,"hbp":0,"so":0,"avg":1},{"batterId":"제주고_정수호_27","batterName":"정수호","pitcherId":"부산고_이승민_18","pitcherName":"이승민","pa":1,"ab":0,"h":0,"b2":0,"b3":0,"hr":0,"bb":1,"hbp":0,"so":0,"avg":0},{"batterId":"제주고_정수호_27","batterName":"정수호","pitcherId":"개성고_이진형_15","pitcherName":"이진형","pa":1,"ab":1,"h":0,"b2":0,"b3":0,"hr":0,"bb":0,"hbp":0,"so":0,"avg":0},{"batterId":"제주고_정수호_27","batterName":"정수호","pitcherId":"경기항공고_이태성_1","pitcherName":"이태성","pa":3,"ab":3,"h":0,"b2":0,"b3":0,"hr":0,"bb":0,"hbp":0,"so":0,"avg":0},{"batterId":"제주고_정수호_27","batterName":"정수호","pitcherId":"부산공업고_정태균_14","pitcherName":"정태균","pa":4,"ab":4,"h":1,"b2":0,"b3":0,"hr":0,"bb":0,"hbp":0,"so":2,"avg":0.25},{"batterId":"제주고_정수호_27","batterName":"정수호","pitcherId":"라온고_조성철_55","pitcherName":"조성철","pa":1,"ab":1,"h":0,"b2":0,"b3":0,"hr":0,"bb":0,"hbp":0,"so":1,"avg":0},{"batterId":"제주고_정수호_27","batterName":"정수호","pitcherId":"라온고_조승용_49","pitcherName":"조승용","pa":2,"ab":2,"h":1,"b2":0,"b3":0,"hr":0,"bb":0,"hbp":0,"so":0,"avg":0.5},{"batterId":"제주고_정수호_27","batterName":"정수호","pitcherId":"서울자동차고_조의탐_18","pitcherName":"조의탐","pa":2,"ab":2,"h":0,"b2":0,"b3":0,"hr":0,"bb":0,"hbp":0,"so":2,"avg":0},{"batterId":"제주고_정수호_27","batterName":"정수호","pitcherId":"경남고_차유주_21","pitcherName":"차유주","pa":2,"ab":2,"h":0,"b2":0,"b3":0,"hr":0,"bb":0,"hbp":0,"so":0,"avg":0},{"batterId":"제주고_정수호_27","batterName":"정수호","pitcherId":"부경고_차효준_26","pitcherName":"차효준","pa":5,"ab":3,"h":0,"b2":0,"b3":0,"hr":0,"bb":1,"hbp":1,"so":0,"avg":0},{"batterId":"제주고_정수호_27","batterName":"정수호","pitcherId":"개성고_최은혁_29","pitcherName":"최은혁","pa":1,"ab":1,"h":0,"b2":0,"b3":0,"hr":0,"bb":0,"hbp":0,"so":0,"avg":0},{"batterId":"제주고_정수호_27","batterName":"정수호","pitcherId":"경기항공고_황재원_31","pitcherName":"황재원","pa":1,"ab":1,"h":0,"b2":0,"b3":0,"hr":0,"bb":0,"hbp":0,"so":0,"avg":0},{"batterId":"개성고_조정훈_25","batterName":"조정훈","pitcherId":"제주고_정수호_27","pitcherName":"정수호","pa":1,"ab":0,"h":0,"b2":0,"b3":0,"hr":0,"bb":0,"hbp":1,"so":0,"avg":0},{"batterId":"개성고_하지운_8","batterName":"하지운","pitcherId":"제주고_정수호_27","pitcherName":"정수호","pa":1,"ab":1,"h":1,"b2":0,"b3":0,"hr":0,"bb":0,"hbp":0,"so":0,"avg":1},{"batterId":"개성고_한승수_16","batterName":"한승수","pitcherId":"제주고_정수호_27","pitcherName":"정수호","pa":1,"ab":0,"h":0,"b2":0,"b3":0,"hr":0,"bb":1,"hbp":0,"so":0,"avg":0}]