{"personNo":"201807002547","name":"김영준","number":"19","birth":"2007.03.20","height":"182","weight":"82","position":"투수","throws":"우","bats":"우","schools":[{"year":2026,"region":"충남","school":"공주고","position":"투수"},{"year":2025,"region":"충남","school":"공주고","position":"투수"},{"year":2024,"region":"충남","school":"공주고","position":"투수"},{"year":2023,"region":"전남","school":"전남 순천이수중"},{"year":2022,"region":"전남","school":"전남 순천이수중"},{"year":2021,"region":"전남","school":"전남 순천이수중"},{"year":2020,"region":"전남","school":"전남 순천남산초"}],"awards":[],"updatedAt":"2026-07-02T00:26:17.916Z"}