{"personNo":"201902000068","name":"정환희","number":"7","birth":"2008.04.20","height":"190","weight":"88","position":"투수","throws":"우","bats":"우","schools":[{"year":2026,"region":"대구","school":"경북고","position":"투수"},{"year":2025,"region":"대구","school":"경북고","position":"투수"},{"year":2024,"region":"대구","school":"경북고","position":"투수"},{"year":2023,"region":"대구","school":"대구 대구중"},{"year":2022,"region":"대구","school":"대구 대구중"},{"year":2021,"region":"대구","school":"대구 대구중"}],"awards":[],"updatedAt":"2026-07-02T00:26:21.297Z"}