{"personNo":"201902004501","name":"유경탁","number":"18","birth":"2008.07.28","height":"185","weight":"90","position":"투수","throws":"우","bats":"우","schools":[{"year":2026,"region":"경북","school":"도개고","position":"투수"},{"year":2025,"region":"경남","school":"김해고","position":"투수"},{"year":2024,"region":"경남","school":"김해고","position":"투수"},{"year":2023,"region":"경남","school":"경남 신월중"},{"year":2022,"region":"경남","school":"경남 신월중"},{"year":2021,"region":"경남","school":"경남 신월중"},{"year":2020,"region":"경남","school":"경남 무학초"},{"year":2019,"region":"경남","school":"경남 무학초"}],"awards":[],"updatedAt":"2026-07-10T09:36:40.063Z","careerYears":{"2026":"도개고_유경탁_18"}}