{"personNo":"202002005077","name":"조승준","number":"8","birth":"2007.10.04","height":"182","weight":"85","position":"외야수","throws":"우","bats":"우","schools":[{"year":2026,"region":"세종","school":"홍익대","position":"외야수"},{"year":2025,"region":"서울","school":"서울고","position":"외야수"},{"year":2024,"region":"서울","school":"서울고","position":"외야수"},{"year":2023,"region":"서울","school":"서울고","position":"외야수"},{"year":2022,"region":"서울","school":"서울 신월중"},{"year":2021,"region":"서울","school":"서울 신월중"},{"year":2020,"region":"서울","school":"서울 신월중"}],"awards":[],"updatedAt":"2026-07-13T00:40:18.661Z","careerYears":{"2024":"서울고_조승준_24","2025":"서울고_조승준_24"}}